Workbook
Name Slicer_Channel: #N/A
Name Slicer_Country: #N/A
Name Slicer_OrderMonth: #N/A
Name Slicer_ProductCategory: #N/A
Name Slicer_Region: #N/A
Name Slicer_Salesperson: #N/A

Sheet COHORT ANALYSIS_FIRST MONTH
A1: Sum of GrossRevenue | B1: Column Labels
A2: Row Labels | B2: Apr-2023 | C2: Apr-2024 | D2: Apr-2025 | E2: Aug-2023 | F2: Aug-2024 | G2: Aug-2025 | H2: Dec-2023 | I2: Dec-2024 | J2: Feb-2023 | K2: Feb-2024 | L2: Feb-2025 | M2: Jan-2023 | N2: Jan-2024 | O2: Jan-2025 | P2: Jul-2023 | Q2: Jul-2024 | R2: Jul-2025 | S2: Jun-2023 | T2: Jun-2024 | U2: Jun-2025 | V2: Mar-2023 | W2: Mar-2024 | X2: Mar-2025 | Y2: May-2023 | Z2: May-2024 | AA2: May-2025 | AB2: Nov-2023 | AC2: Nov-2024 | AD2: Oct-2023 | AE2: Oct-2024 | AF2: Sep-2023 | AG2: Sep-2024 | AH2: Sep-2025 | AI2: (blank) | AJ2: Grand Total
A3: Brazil | B3: 12248.676 | C3: 57491.063 | D3: 68920.107 | E3: 37330.003 | F3: 41358.42 | G3: 45754.744 | H3: 61471.697 | J3: 24894.431 | K3: 39239.198 | L3: 70563.592 | M3: 1801.4076 | N3: 8567.3925 | O3: 22987.328 | P3: 93430.735 | Q3: 10937.52 | R3: 38096.184 | S3: 46991.747 | T3: 41658.527 | V3: 24523.007 | W3: 110.1492 | X3: 16257.34 | Y3: 27194.152 | Z3: 9469.7678 | AA3: 67596.422 | AB3: 24161.263 | AC3: 11939.431 | AD3: 16213.633 | AF3: 7071.6331 | AG3: 85419.018 | AH3: 24172.045 | AJ3: 1037870.6
A4: Canada | B4: 15618.845 | D4: 7901.5042 | E4: 52625.804 | F4: 7466.3064 | G4: 24972.288 | H4: 14466.951 | I4: 20713.04 | J4: 26150.364 | K4: 9774.3888 | L4: 8128.5187 | M4: 4141.76 | N4: 19139.594 | P4: 29536.716 | Q4: 79082.507 | R4: 141645.57 | S4: 46226.12 | T4: 55516.604 | U4: 5335.5655 | V4: 17453.344 | W4: 21931.504 | Z4: 17930.495 | AA4: 76122.593 | AC4: 60697.471 | AD4: 27756.432 | AF4: 15530.93 | AG4: 64160.245 | AH4: 12597.522 | AJ4: 882622.98
A5: China | B5: 23379.011 | C5: 14197.064 | E5: 64096.735 | G5: 33684.351 | H5: 23668.56 | I5: 77129.274 | J5: 10869.183 | K5: 79081.561 | M5: 11406.96 | O5: 56274.474 | Q5: 50774.407 | R5: 20703.052 | S5: 5769.2758 | T5: 70180.56 | U5: 55548.647 | V5: 13437.3 | W5: 45749.976 | X5: 9378.6258 | Y5: 49097.717 | AA5: 9684.8756 | AC5: 4071.8 | AD5: 66630.072 | AE5: 68861.98 | AF5: 14108.168 | AG5: 21270.483 | AJ5: 899054.11
A6: France | B6: 40811.052 | C6: 16219.345 | D6: 33208.325 | E6: 36549.429 | F6: 9189.1635 | G6: 68199.913 | H6: 28412.1 | I6: 32011.667 | J6: 39546.775 | K6: 20654.545 | L6: 12040.644 | M6: 9847.2359 | N6: 29263.361 | O6: 20050.102 | P6: 60768.603 | Q6: 27907.425 | S6: 10388.43 | U6: 81482.872 | W6: 45104.931 | Z6: 43635.435 | AA6: 5331.6696 | AB6: 22983.346 | AC6: 67281.057 | AD6: 5159.7894 | AE6: 41419.524 | AF6: 14877.464 | AJ6: 822344.2
A7: Germany | B7: 104633.05 | C7: 37482.346 | D7: 5810.4845 | E7: 215.1984 | F7: 47066.844 | G7: 56176.778 | H7: 56963.241 | I7: 78869.294 | J7: 142962.67 | K7: 321.93291 | L7: 30546.068 | M7: 13921.506 | N7: 41020.91 | P7: 14114.069 | S7: 5189.8836 | T7: 65111.386 | U7: 56166.984 | V7: 6271.3802 | W7: 68292.728 | X7: 16870.42 | Y7: 17964.404 | Z7: 32187.988 | AA7: 10666.229 | AB7: 7643.265 | AC7: 12955.825 | AJ7: 929424.89
A8: India | B8: 32506.559 | D8: 4856.3573 | E8: 7105.3528 | F8: 44186.459 | G8: 11006.648 | H8: 35984.637 | I8: 40695.915 | J8: 22044.871 | K8: 24305.883 | L8: 7120.6486 | M8: 26759.288 | N8: 33792.866 | O8: 33308.55 | P8: 12462.651 | Q8: 30229.995 | S8: 4577.148 | T8: 31513.423 | U8: 39717.144 | V8: 6631.6443 | W8: 12668.507 | X8: 24075.09 | Y8: 249678.14 | Z8: 35554.1 | AA8: 62421.225 | AB8: 39388.574 | AC8: 91856.869 | AD8: 34805.041 | AE8: 599.532 | AF8: 42824.197 | AG8: 20028.787 | AH8: 29627.32 | AJ8: 1092333.4
A9: Japan | B9: 21196.913 | D9: 20606.464 | F9: 82602.55 | G9: 34082.865 | H9: 38506.529 | I9: 18641.222 | K9: 15253.07 | L9: 7955.6342 | N9: 67110.666 | O9: 15705.464 | P9: 32142.114 | Q9: 23449.834 | R9: 9315.4974 | S9: 4603.0824 | T9: 68665.574 | U9: 11984.891 | V9: 31024.839 | X9: 49818.787 | Y9: 9062.3469 | Z9: 14287.896 | AA9: 63856.507 | AB9: 14268.608 | AD9: 14527.748 | AE9: 29808.425 | AF9: 31130.742 | AG9: 50582.706 | AH9: 74882.386 | AJ9: 855073.36
A10: Kenya | B10: 11003.767 | C10: 24447.959 | D10: 17731.623 | E10: 667.74 | F10: 3823.6152 | G10: 15174.426 | H10: 16061.973 | J10: 17866.938 | K10: 66852.129 | L10: 15860.782 | M10: 47962.718 | O10: 52609.066 | P10: 47047.518 | Q10: 27763.018 | R10: 17867.219 | S10: 3799.8031 | T10: 181608.7 | V10: 70602.928 | W10: 4866.3288 | X10: 13669.81 | Y10: 10946.712 | Z10: 13108.786 | AA10: 4569.8508 | AC10: 123535.74 | AD10: 38264.51 | AE10: 51457.54 | AF10: 1030.7574 | AG10: 52863.981 | AH10: 9050.5053 | AJ10: 962116.44
A11: Nigeria | B11: 32280.325 | C11: 48850.807 | D11: 40139.875 | E11: 24833.098 | G11: 49501.66 | H11: 27158.894 | I11: 12967.959 | J11: 4737.2198 | L11: 23687.576 | M11: 685.06776 | P11: 112088.82 | R11: 119970.85 | S11: 7135.57 | T11: 15009.057 | U11: 55110.62 | W11: 28041.025 | X11: 52727.976 | Y11: 43539.233 | Z11: 68626.652 | AA11: 1010.3759 | AD11: 10786.321 | AE11: 100069.72 | AG11: 2879.9836 | AJ11: 881838.68
A12: South Africa | C12: 20171.633 | D12: 1886.9916 | E12: 58520.37 | F12: 27331.83 | H12: 79406.785 | J12: 86597.081 | M12: 3116.21 | N12: 54214.972 | O12: 6576.299 | P12: 78566.393 | R12: 76636.156 | T12: 39907.476 | U12: 88311.187 | V12: 29618.551 | W12: 4826.5396 | X12: 5565.3273 | Y12: 15476.944 | Z12: 14032.851 | AA12: 31556.188 | AB12: 12954.358 | AD12: 434.45248 | AE12: 18061.204 | AG12: 12972.002 | AH12: 13185.543 | AJ12: 779927.34
A13: United Kingdom | B13: 66551.125 | C13: 20646.611 | D13: 96832.738 | E13: 31801.901 | F13: 23687.524 | G13: 853.32277 | I13: 90699.331 | J13: 4132.0325 | L13: 35720.318 | M13: 27965.367 | N13: 27424.45 | O13: 11332.143 | P13: 48616.566 | R13: 62736.309 | S13: 29905.538 | T13: 65319.42 | U13: 52414.751 | V13: 16013.682 | W13: 33938.143 | X13: 21062.612 | Y13: 19800.889 | Z13: 114279.15 | AA13: 39263.703 | AB13: 5610.0924 | AC13: 44605.989 | AD13: 26003.218 | AE13: 91431.438 | AG13: 25249.613 | AH13: 8764.4066 | AJ13: 1142662.4
A14: USA | B14: 11375.258 | D14: 38240.697 | E14: 25299.04 | F14: 97443.478 | G14: 27401.728 | I14: 12031.492 | J14: 68738.647 | K14: 52311.008 | L14: 9984.7161 | M14: 31035.218 | N14: 18566.16 | O14: 4654.7743 | P14: 32086.376 | Q14: 25483.915 | S14: 71887.464 | W14: 108770.28 | Y14: 27431.638 | Z14: 53872.641 | AA14: 3644.3213 | AD14: 5533.623 | AE14: 16023.123 | AF14: 14692.623 | AG14: 12186.369 | AJ14: 768694.59
A15: (blank)
A16: Grand Total | B16: 371604.58 | C16: 239506.83 | D16: 336135.17 | E16: 339044.67 | F16: 384156.19 | G16: 366808.72 | H16: 382101.37 | I16: 383759.19 | J16: 448540.22 | K16: 307793.71 | L16: 221608.5 | M16: 178642.74 | N16: 299100.37 | O16: 223498.2 | P16: 560860.56 | Q16: 275628.62 | R16: 486970.83 | S16: 236474.06 | T16: 634490.72 | U16: 446072.66 | V16: 215576.67 | W16: 374300.11 | X16: 209425.99 | Y16: 470192.17 | Z16: 416985.77 | AA16: 375723.96 | AB16: 127009.51 | AC16: 416944.19 | AD16: 246114.84 | AE16: 417732.48 | AF16: 141266.51 | AG16: 347613.19 | AH16: 172279.73 | AJ16: 11053963

Sheet Sheet5
A3: Row Labels | B3: Sum of GrossRevenue
A4: Accessories
A5: ACC-6626 | B5: 0.056242052 | C5: =IF(B5<=0.8,"A",IF(B5<=0.95,"B","C")) -> A
A6: ACC-1770 | B6: 0.10199685 | C6: =IF(B6<=0.8,"A",IF(B6<=0.95,"B","C")) -> A
A7: ACC-2988 | B7: 0.13971393 | C7: =IF(B7<=0.8,"A",IF(B7<=0.95,"B","C")) -> A
A8: ACC-9283 | B8: 0.17274852 | C8: =IF(B8<=0.8,"A",IF(B8<=0.95,"B","C")) -> A
A9: ACC-9533 | B9: 0.2033897 | C9: =IF(B9<=0.8,"A",IF(B9<=0.95,"B","C")) -> A
A10: ACC-8098 | B10: 0.23048302 | C10: =IF(B10<=0.8,"A",IF(B10<=0.95,"B","C")) -> A
A11: ACC-4490 | B11: 0.25565621 | C11: =IF(B11<=0.8,"A",IF(B11<=0.95,"B","C")) -> A
A12: ACC-7838 | B12: 0.28066688 | C12: =IF(B12<=0.8,"A",IF(B12<=0.95,"B","C")) -> A
A13: ACC-5177 | B13: 0.30494603 | C13: =IF(B13<=0.8,"A",IF(B13<=0.95,"B","C")) -> A
A14: ACC-9162 | B14: 0.3284593 | C14: =IF(B14<=0.8,"A",IF(B14<=0.95,"B","C")) -> A
A15: ACC-7078 | B15: 0.35127855 | C15: =IF(B15<=0.8,"A",IF(B15<=0.95,"B","C")) -> A
A16: ACC-1375 | B16: 0.37369009 | C16: =IF(B16<=0.8,"A",IF(B16<=0.95,"B","C")) -> A
... A92: ACC-6777 | B92: 1 | C92: =IF(B92<=0.8,"A",IF(B92<=0.95,"B","C")) -> C
A93: Components | C93: =IF(B93<=0.8,"A",IF(B93<=0.95,"B","C")) -> A
A94: CMP-8851 | B94: 0.089845041 | C94: =IF(B94<=0.8,"A",IF(B94<=0.95,"B","C")) -> A
A95: CMP-3938 | B95: 0.14411939 | C95: =IF(B95<=0.8,"A",IF(B95<=0.95,"B","C")) -> A
A96: CMP-2040 | B96: 0.1861213 | C96: =IF(B96<=0.8,"A",IF(B96<=0.95,"B","C")) -> A
A97: CMP-3731 | B97: 0.22542492 | C97: =IF(B97<=0.8,"A",IF(B97<=0.95,"B","C")) -> A
A98: CMP-2096 | B98: 0.25920226 | C98: =IF(B98<=0.8,"A",IF(B98<=0.95,"B","C")) -> A
A99: CMP-8127 | B99: 0.29164736 | C99: =IF(B99<=0.8,"A",IF(B99<=0.95,"B","C")) -> A
A100: CMP-5006 | B100: 0.31836618 | C100: =IF(B100<=0.8,"A",IF(B100<=0.95,"B","C")) -> A
A101: CMP-1940 | B101: 0.34447636 | C101: =IF(B101<=0.8,"A",IF(B101<=0.95,"B","C")) -> A
A102: CMP-8002 | B102: 0.36620742 | C102: =IF(B102<=0.8,"A",IF(B102<=0.95,"B","C")) -> A
A103: CMP-1156 | B103: 0.38769403 | C103: =IF(B103<=0.8,"A",IF(B103<=0.95,"B","C")) -> A
A104: CMP-6529 | B104: 0.40855276 | C104: =IF(B104<=0.8,"A",IF(B104<=0.95,"B","C")) -> A
A105: CMP-6971 | B105: 0.42642243 | C105: =IF(B105<=0.8,"A",IF(B105<=0.95,"B","C")) -> A
... A183: CMP-1632 | B183: 1 | C183: =IF(B183<=0.8,"A",IF(B183<=0.95,"B","C")) -> C
A184: Laptops | B184: #N/A | C184: =IF(B184<=0.8,"A",IF(B184<=0.95,"B","C")) -> #N/A
A185: Monitors | B185: #N/A | C185: =IF(B185<=0.8,"A",IF(B185<=0.95,"B","C")) -> #N/A
A186: Networking | B186: #N/A | C186: =IF(B186<=0.8,"A",IF(B186<=0.95,"B","C")) -> #N/A
A187: Phones | C187: =IF(B187<=0.8,"A",IF(B187<=0.95,"B","C")) -> A
A188: PHN-9677 | B188: 0.049073401 | C188: =IF(B188<=0.8,"A",IF(B188<=0.95,"B","C")) -> A
A189: PHN-8368 | B189: 0.086793868 | C189: =IF(B189<=0.8,"A",IF(B189<=0.95,"B","C")) -> A
A190: PHN-4568 | B190: 0.11716445 | C190: =IF(B190<=0.8,"A",IF(B190<=0.95,"B","C")) -> A
A191: PHN-7488 | B191: 0.14671777 | C191: =IF(B191<=0.8,"A",IF(B191<=0.95,"B","C")) -> A
A192: PHN-5683 | B192: 0.17611815 | C192: =IF(B192<=0.8,"A",IF(B192<=0.95,"B","C")) -> A
A193: PHN-4915 | B193: 0.20357732 | C193: =IF(B193<=0.8,"A",IF(B193<=0.95,"B","C")) -> A
A194: PHN-8804 | B194: 0.23004778 | C194: =IF(B194<=0.8,"A",IF(B194<=0.95,"B","C")) -> A
A195: PHN-1197 | B195: 0.25532375 | C195: =IF(B195<=0.8,"A",IF(B195<=0.95,"B","C")) -> A
A196: PHN-6832 | B196: 0.28022319 | C196: =IF(B196<=0.8,"A",IF(B196<=0.95,"B","C")) -> A
A197: PHN-8776 | B197: 0.3050941 | C197: =IF(B197<=0.8,"A",IF(B197<=0.95,"B","C")) -> A
A198: PHN-6111 | B198: 0.32907274 | C198: =IF(B198<=0.8,"A",IF(B198<=0.95,"B","C")) -> A
A199: PHN-1919 | B199: 0.3527079 | C199: =IF(B199<=0.8,"A",IF(B199<=0.95,"B","C")) -> A
... A275: PHN-3803 | B275: 1 | C275: =IF(B275<=0.8,"A",IF(B275<=0.95,"B","C")) -> C
A276: Printers | C276: =IF(B276<=0.8,"A",IF(B276<=0.95,"B","C")) -> A
A277: PRN-1654 | B277: 0.040979589 | C277: =IF(B277<=0.8,"A",IF(B277<=0.95,"B","C")) -> A
A278: PRN-6308 | B278: 0.076907147 | C278: =IF(B278<=0.8,"A",IF(B278<=0.95,"B","C")) -> A
A279: PRN-7019 | B279: 0.11146719 | C279: =IF(B279<=0.8,"A",IF(B279<=0.95,"B","C")) -> A
A280: PRN-2407 | B280: 0.14272763 | C280: =IF(B280<=0.8,"A",IF(B280<=0.95,"B","C")) -> A
A281: PRN-9490 | B281: 0.16988309 | C281: =IF(B281<=0.8,"A",IF(B281<=0.95,"B","C")) -> A
A282: PRN-8970 | B282: 0.19660628 | C282: =IF(B282<=0.8,"A",IF(B282<=0.95,"B","C")) -> A
A283: PRN-2293 | B283: 0.22154601 | C283: =IF(B283<=0.8,"A",IF(B283<=0.95,"B","C")) -> A
A284: PRN-6131 | B284: 0.24616725 | C284: =IF(B284<=0.8,"A",IF(B284<=0.95,"B","C")) -> A
A285: PRN-5384 | B285: 0.27000033 | C285: =IF(B285<=0.8,"A",IF(B285<=0.95,"B","C")) -> A
A286: PRN-5876 | B286: 0.29323123 | C286: =IF(B286<=0.8,"A",IF(B286<=0.95,"B","C")) -> A
A287: PRN-7079 | B287: 0.31583572 | C287: =IF(B287<=0.8,"A",IF(B287<=0.95,"B","C")) -> A
A288: PRN-4911 | B288: 0.33783307 | C288: =IF(B288<=0.8,"A",IF(B288<=0.95,"B","C")) -> A
... A379: PRN-6276 | B379: 1 | C379: =IF(B379<=0.8,"A",IF(B379<=0.95,"B","C")) -> C
A380: (blank) | C380: =IF(B380<=0.8,"A",IF(B380<=0.95,"B","C")) -> A
A381: (blank) | C381: =IF(B381<=0.8,"A",IF(B381<=0.95,"B","C")) -> A
A382: Grand Total | C382: =IF(B382<=0.8,"A",IF(B382<=0.95,"B","C")) -> A
C383: =IF(B383<=0.8,"A",IF(B383<=0.95,"B","C")) -> A
C384: =IF(B384<=0.8,"A",IF(B384<=0.95,"B","C")) -> A
C385: =IF(B385<=0.8,"A",IF(B385<=0.95,"B","C")) -> A
C386: =IF(B386<=0.8,"A",IF(B386<=0.95,"B","C")) -> A
C387: =IF(B387<=0.8,"A",IF(B387<=0.95,"B","C")) -> A
C388: =IF(B388<=0.8,"A",IF(B388<=0.95,"B","C")) -> A
C389: =IF(B389<=0.8,"A",IF(B389<=0.95,"B","C")) -> A
C390: =IF(B390<=0.8,"A",IF(B390<=0.95,"B","C")) -> A
C391: =IF(B391<=0.8,"A",IF(B391<=0.95,"B","C")) -> A
C392: =IF(B392<=0.8,"A",IF(B392<=0.95,"B","C")) -> A
C393: =IF(B393<=0.8,"A",IF(B393<=0.95,"B","C")) -> A
C394: =IF(B394<=0.8,"A",IF(B394<=0.95,"B","C")) -> A
... C640: =IF(B640<=0.8,"A",IF(B640<=0.95,"B","C")) -> A

Sheet Sheet7
A1: ACC-6626 | B1: 79082.507 | C1: =B2/$H$1 -> 0.045754795 | D1: =SUM($C$2:C2) -> 0.037717083 | H1: =SUM(B:B) -> 1406109.9
A2: ACC-1770 | B2: 64336.271 | C2: =B3/$H$1 -> 0.037717083 | D2: =SUM($C$2:C3) -> 0.07075167
A3: ACC-2988 | B3: 53034.364 | C3: =B4/$H$1 -> 0.033034587 | D3: =SUM($C$2:C4) -> 0.10139285
A4: ACC-9283 | B4: 46450.26 | C4: =B5/$H$1 -> 0.030641184 | D4: =SUM($C$2:C5) -> 0.12848617
A5: ACC-9533 | B5: 43084.872 | C5: =B6/$H$1 -> 0.027093319 | D5: =SUM($C$2:C6) -> 0.15365937
A6: ACC-8098 | B6: 38096.184 | C6: =B7/$H$1 -> 0.025173194 | D6: =SUM($C$2:C7) -> 0.17867003
A7: ACC-4490 | B7: 35396.278 | C7: =B8/$H$1 -> 0.025010666 | D7: =SUM($C$2:C8) -> 0.20294919
A8: ACC-7838 | B8: 35167.745 | C8: =B9/$H$1 -> 0.024279155 | D8: =SUM($C$2:C9) -> 0.22646245
A9: ACC-5177 | B9: 34139.16 | C9: =B10/$H$1 -> 0.023513266 | D9: =SUM($C$2:C10) -> 0.2492817
A10: ACC-9162 | B10: 33062.236 | C10: =B11/$H$1 -> 0.022819252 | D10: =SUM($C$2:C11) -> 0.27169324
A11: ACC-7078 | B11: 32086.376 | C11: =B12/$H$1 -> 0.022411538 | D11: =SUM($C$2:C12) -> 0.29188086
A12: ACC-1375 | B12: 31513.085 | C12: =B13/$H$1 -> 0.020187622 | D12: =SUM($C$2:C13) -> 0.31141394
A13: ACC-1659 | B13: 28386.016 | C13: =B14/$H$1 -> 0.019533073 | D13: =SUM($C$2:C14) -> 0.33044875
... A88: ACC-6777 | B88: 18.65984 | C88: =B89/$H$1 -> 0 | D88: =SUM($C$2:C89) -> 0.89800315

Sheet REVENUE PER ORDER
A3: Row Labels | B3: Sum of GrossRevenue | C3: Count of OrderID
A4: A. Patel | B4: 877449.32 | C4: 46
A5: B. Chen | B5: 893735.66 | C5: 48
A6: C. Otieno | B6: 689776.36 | C6: 37
A7: D. Smith | B7: 606200.45 | C7: 38
A8: E. Garcia | B8: 543846.44 | C8: 34
A9: F. Müller | B9: 812637.17 | C9: 51
A10: G. Dubois | B10: 510653.71 | C10: 30
A11: H. Kim | B11: 762763.59 | C11: 45
A12: I. Johnson | B12: 555917.25 | C12: 38
A13: J. Njeri | B13: 802384.66 | C13: 50
A14: K. Singh | B14: 883348.13 | C14: 44
A15: L. Okafor | B15: 853476.7 | C15: 46
... A19: Unassigned | B19: 249026.85 | C19: 8
A20: (blank)
A21: Grand Total | B21: 11053963 | C21: 632

Sheet Sheet10
A3: Count of OrderID | B3: Column Labels
A4: Row Labels | B4: Apr-2023 | C4: Apr-2024 | D4: Apr-2025 | E4: Aug-2023 | F4: Aug-2024 | G4: Aug-2025 | H4: Dec-2023 | I4: Dec-2024 | J4: Feb-2023 | K4: Feb-2024 | L4: Feb-2025 | M4: Jan-2023 | N4: Jan-2024 | O4: Jan-2025 | P4: Jul-2023 | Q4: Jul-2024 | R4: Jul-2025 | S4: Jun-2023 | T4: Jun-2024 | U4: Jun-2025 | V4: Mar-2023 | W4: Mar-2024 | X4: Mar-2025 | Y4: May-2023 | Z4: May-2024 | AA4: May-2025 | AB4: Nov-2023 | AC4: Nov-2024 | AD4: Oct-2023 | AE4: Oct-2024 | AF4: Sep-2023 | AG4: Sep-2024 | AH4: Sep-2025 | AI4: (blank) | AJ4: Grand Total
A5: A. Patel | B5: 4 | C5: 3 | E5: 1 | G5: 3 | H5: 3 | K5: 3 | M5: 2 | N5: 3 | P5: 2 | Q5: 1 | S5: 2 | T5: 1 | U5: 3 | V5: 2 | Y5: 2 | Z5: 1 | AA5: 3 | AC5: 2 | AD5: 1 | AE5: 1 | AF5: 1 | AG5: 1 | AH5: 1 | AJ5: 46
A6: B. Chen | B6: 1 | C6: 1 | D6: 1 | E6: 2 | F6: 1 | G6: 2 | H6: 1 | I6: 3 | K6: 1 | L6: 2 | M6: 2 | N6: 4 | O6: 3 | P6: 4 | R6: 2 | T6: 1 | U6: 1 | V6: 1 | W6: 1 | X6: 1 | Y6: 1 | Z6: 2 | AA6: 1 | AC6: 2 | AE6: 2 | AF6: 4 | AG6: 1 | AJ6: 48
A7: C. Otieno | C7: 1 | D7: 2 | F7: 2 | H7: 1 | I7: 1 | J7: 1 | K7: 1 | L7: 1 | N7: 1 | O7: 1 | P7: 2 | R7: 1 | S7: 2 | T7: 1 | U7: 2 | V7: 3 | W7: 1 | X7: 2 | Y7: 1 | Z7: 2 | AA7: 1 | AB7: 1 | AC7: 1 | AD7: 2 | AE7: 1 | AH7: 2 | AJ7: 37
A8: D. Smith | B8: 1 | C8: 2 | D8: 1 | E8: 1 | F8: 3 | H8: 2 | I8: 3 | J8: 3 | K8: 1 | L8: 2 | M8: 2 | N8: 1 | P8: 1 | Q8: 1 | R8: 1 | T8: 1 | U8: 1 | V8: 2 | X8: 1 | Y8: 1 | Z8: 1 | AC8: 1 | AF8: 2 | AG8: 2 | AH8: 1 | AJ8: 38
A9: E. Garcia | B9: 4 | C9: 1 | D9: 1 | F9: 1 | G9: 3 | H9: 1 | I9: 1 | K9: 1 | N9: 3 | O9: 1 | P9: 1 | S9: 2 | U9: 1 | W9: 1 | X9: 2 | Y9: 3 | Z9: 2 | AB9: 1 | AC9: 1 | AE9: 2 | AG9: 1 | AJ9: 34
A10: F. Müller | D10: 4 | E10: 2 | F10: 1 | G10: 2 | H10: 1 | I10: 2 | J10: 1 | K10: 2 | L10: 1 | M10: 1 | N10: 1 | O10: 2 | P10: 3 | Q10: 3 | S10: 3 | T10: 2 | W10: 2 | X10: 1 | Y10: 2 | Z10: 3 | AA10: 3 | AB10: 1 | AC10: 2 | AD10: 1 | AE10: 3 | AG10: 1 | AH10: 1 | AJ10: 51
A11: G. Dubois | B11: 1 | D11: 2 | E11: 1 | I11: 1 | K11: 1 | M11: 2 | N11: 2 | O11: 1 | P11: 1 | Q11: 2 | R11: 1 | T11: 1 | U11: 2 | V11: 1 | W11: 3 | X11: 3 | Y11: 1 | Z11: 1 | AA11: 1 | AC11: 1 | AD11: 1 | AJ11: 30
A12: H. Kim | B12: 2 | D12: 2 | F12: 2 | H12: 1 | I12: 1 | J12: 1 | K12: 3 | L12: 1 | M12: 1 | N12: 1 | O12: 2 | Q12: 1 | R12: 2 | S12: 1 | T12: 2 | U12: 2 | W12: 1 | X12: 4 | Y12: 1 | Z12: 3 | AA12: 3 | AB12: 2 | AC12: 1 | AD12: 1 | AE12: 2 | AG12: 2 | AJ12: 45
A13: I. Johnson | B13: 1 | D13: 2 | E13: 1 | F13: 2 | G13: 2 | J13: 1 | K13: 1 | L13: 1 | N13: 1 | O13: 1 | P13: 2 | Q13: 1 | R13: 2 | S13: 2 | T13: 1 | U13: 1 | V13: 2 | W13: 4 | X13: 1 | Z13: 1 | AC13: 2 | AD13: 3 | AE13: 1 | AF13: 2 | AJ13: 38
A14: J. Njeri | B14: 1 | D14: 1 | E14: 3 | F14: 2 | G14: 1 | H14: 1 | I14: 2 | N14: 1 | O14: 1 | P14: 1 | Q14: 4 | R14: 1 | S14: 3 | T14: 3 | U14: 1 | V14: 1 | W14: 1 | X14: 3 | Y14: 4 | AA14: 2 | AC14: 1 | AD14: 4 | AE14: 3 | AF14: 3 | AG14: 1 | AH14: 1 | AJ14: 50
A15: K. Singh | B15: 1 | C15: 2 | D15: 4 | E15: 1 | F15: 1 | G15: 1 | H15: 2 | I15: 3 | J15: 3 | K15: 2 | L15: 1 | N15: 1 | O15: 1 | R15: 1 | S15: 2 | T15: 1 | V15: 1 | W15: 2 | X15: 1 | Y15: 4 | Z15: 2 | AA15: 1 | AB15: 1 | AD15: 1 | AG15: 3 | AH15: 1 | AJ15: 44
A16: L. Okafor | D16: 1 | E16: 2 | F16: 2 | H16: 4 | I16: 1 | J16: 3 | K16: 1 | L16: 5 | N16: 1 | O16: 2 | P16: 1 | T16: 3 | U16: 2 | V16: 1 | W16: 1 | X16: 1 | Y16: 2 | Z16: 2 | AA16: 1 | AB16: 3 | AC16: 1 | AD16: 1 | AE16: 1 | AG16: 2 | AH16: 2 | AJ16: 46
A17: M. Rossi | B17: 5 | D17: 1 | E17: 1 | F17: 1 | G17: 3 | H17: 1 | I17: 2 | J17: 3 | M17: 2 | P17: 2 | Q17: 1 | R17: 3 | S17: 1 | T17: 4 | U17: 3 | W17: 4 | Y17: 3 | Z17: 1 | AA17: 1 | AC17: 2 | AE17: 2 | AG17: 1 | AH17: 1 | AJ17: 48
A18: N. Brown | B18: 1 | C18: 3 | D18: 3 | E18: 6 | F18: 1 | G18: 2 | H18: 2 | J18: 1 | L18: 1 | M18: 1 | N18: 1 | P18: 2 | S18: 1 | U18: 2 | Z18: 1 | AE18: 1 | AG18: 2 | AH18: 1 | AJ18: 32
A19: O. Wang | B19: 2 | C19: 1 | E19: 2 | G19: 2 | H19: 1 | I19: 1 | K19: 1 | L19: 1 | M19: 2 | N19: 1 | O19: 1 | R19: 1 | S19: 2 | T19: 2 | U19: 2 | V19: 1 | W19: 2 | Y19: 1 | Z19: 1 | AA19: 1 | AC19: 3 | AD19: 2 | AE19: 2 | AG19: 1 | AH19: 1 | AJ19: 37
A20: Unassigned | E20: 1 | F20: 1 | N20: 1 | P20: 1 | R20: 1 | U20: 1 | AB20: 1 | AD20: 1 | AJ20: 8
A21: (blank)
A22: Grand Total | B22: 24 | C22: 14 | D22: 25 | E22: 24 | F22: 20 | G22: 21 | H22: 21 | I22: 21 | J22: 17 | K22: 18 | L22: 16 | M22: 15 | N22: 23 | O22: 16 | P22: 23 | Q22: 14 | R22: 16 | S22: 21 | T22: 23 | U22: 24 | V22: 15 | W22: 23 | X22: 20 | Y22: 26 | Z22: 23 | AA22: 18 | AB22: 10 | AC22: 20 | AD22: 18 | AE22: 21 | AF22: 12 | AG22: 18 | AH22: 12 | AJ22: 632

Sheet GROSSPROFIT_SALESPERSON
A3: Row Labels | B3: Sum of GrossProfit | C3: Count of OrderID
A4: A. Patel | B4: 282234.27 | C4: 46
A5: B. Chen | B5: 315969.97 | C5: 48
A6: C. Otieno | B6: 230359.52 | C6: 37
A7: D. Smith | B7: 180457.19 | C7: 38
A8: E. Garcia | B8: 204981.34 | C8: 34
A9: F. Müller | B9: 251733.01 | C9: 51
A10: G. Dubois | B10: 172441.87 | C10: 30
A11: H. Kim | B11: 202216.1 | C11: 45
A12: I. Johnson | B12: 154773.27 | C12: 38
A13: J. Njeri | B13: 273113.11 | C13: 50
A14: K. Singh | B14: 278762.27 | C14: 44
A15: L. Okafor | B15: 270154.73 | C15: 46
... A19: Unassigned | B19: 100098 | C19: 8
A20: (blank)
A21: Grand Total | B21: 3526215.3 | C21: 632

Sheet Channel Mix & Cannibalization
A3: Sum of GrossRevenue | B3: Column Labels
A4: Row Labels | B4: Direct | C4: Distributor | D4: Marketplace | E4: Online | F4: Retail | G4: Unknown | H4: (blank) | I4: Grand Total
A5: Africa | B5: 462236.49 | C5: 634581.62 | D5: 527467.87 | E5: 433406.34 | F5: 533473.21 | G5: 32716.924 | I5: 2623882.5
A6: Americas | B6: 751887.69 | C6: 568863.41 | D6: 366375.93 | E6: 689951.45 | F6: 302853.58 | G6: 9256.14 | I6: 2689188.2
A7: Asia | B7: 642753.26 | C7: 509418.81 | D7: 546106.24 | E7: 413661.51 | F7: 693141.68 | G7: 41379.395 | I7: 2846460.9
A8: Europe | B8: 842614.45 | C8: 318736.67 | D8: 633739.82 | E8: 585406.72 | F8: 495883.37 | G8: 18050.446 | I8: 2894431.5
A9: (blank)
A10: Grand Total | B10: 2699491.9 | C10: 2031600.5 | D10: 2073689.9 | E10: 2122426 | F10: 2025351.8 | G10: 101402.91 | I10: 11053963

Sheet SERVICE_LEVEL_PROXY
A3: Row Labels | B3: Count of OnTime_7Days | C3: Count of OrderID | D3: Order Percentage
A4: Brazil | B4: 62 | C4: 62
A5: Accessories | B5: 10 | C5: 10 | D5: =(C5/62)*100 -> 16.129032
A6: Components | B6: 7 | C6: 7 | D6: =(C6/62)*100 -> 11.290323
A7: Laptops | B7: 5 | C7: 5 | D7: =(C7/62)*100 -> 8.0645161
A8: Monitors | B8: 12 | C8: 12 | D8: =(C8/62)*100 -> 19.354839
A9: Networking | B9: 12 | C9: 12 | D9: =(C9/62)*100 -> 19.354839
A10: Phones | B10: 9 | C10: 9 | D10: =(C10/62)*100 -> 14.516129
A11: Printers | B11: 7 | C11: 7 | D11: =(C11/62)*100 -> 11.290323
A12: Canada | B12: 44 | C12: 44
A13: Accessories | B13: 6 | C13: 6
A14: Components | B14: 6 | C14: 6
A15: Laptops | B15: 6 | C15: 6
A16: Monitors | B16: 7 | C16: 7
A17: Networking | B17: 3 | C17: 3
A18: Phones | B18: 3 | C18: 3
A19: Printers | B19: 13 | C19: 13
A20: China | B20: 51 | C20: 51
A21: Accessories | B21: 4 | C21: 4
A22: Components | B22: 10 | C22: 10
A23: Laptops | B23: 5 | C23: 5
... A99: Printers | B99: 8 | C99: 8
A100: (blank)
A101: (blank)
A102: Grand Total | B102: 632 | C102: 632

Sheet What_if_Analysis
A1: What_if Control Panel
A2: Global Discount Cap | B2: 0.05
A3: Unit Cost Inflation | B3: 0.1
A4: Quantity Uplift | B4: 0.2
A5: Baseline Revenue | B5: =SUM(Data!AC:AC) -> 7527747.7
A6: Baseline Profit | B6: =SUM(Data!AD:AD) -> 7052430.6

Sheet PRICE COMPLIANCE
A3: Row Labels | B3: Average of HighDiscount
A4: Americas | B4: 0.17197452
A5: D. Smith | B5: 0.5 | C5: =IF(B5>0.3,"HIGH",IF(B5>0.15,"MEDIUM","LOW")) -> HIGH
A6: A. Patel | B6: 0.5 | C6: =IF(B6>0.3,"HIGH",IF(B6>0.15,"MEDIUM","LOW")) -> HIGH
A7: I. Johnson | B7: 0.35714286 | C7: =IF(B7>0.3,"HIGH",IF(B7>0.15,"MEDIUM","LOW")) -> HIGH
A8: Unassigned | B8: 0.33333333 | C8: =IF(B8>0.3,"HIGH",IF(B8>0.15,"MEDIUM","LOW")) -> HIGH
A9: L. Okafor | B9: 0.25 | C9: =IF(B9>0.3,"HIGH",IF(B9>0.15,"MEDIUM","LOW")) -> MEDIUM
A10: M. Rossi | B10: 0.16666667 | C10: =IF(B10>0.3,"HIGH",IF(B10>0.15,"MEDIUM","LOW")) -> MEDIUM
A11: N. Brown | B11: 0.14285714 | C11: =IF(B11>0.3,"HIGH",IF(B11>0.15,"MEDIUM","LOW")) -> LOW
A12: C. Otieno | B12: 0.14285714 | C12: =IF(B12>0.3,"HIGH",IF(B12>0.15,"MEDIUM","LOW")) -> LOW
A13: G. Dubois | B13: 0.125 | C13: =IF(B13>0.3,"HIGH",IF(B13>0.15,"MEDIUM","LOW")) -> LOW
A14: B. Chen | B14: 0.125 | C14: =IF(B14>0.3,"HIGH",IF(B14>0.15,"MEDIUM","LOW")) -> LOW
A15: K. Singh | B15: 0.1 | C15: =IF(B15>0.3,"HIGH",IF(B15>0.15,"MEDIUM","LOW")) -> LOW
A16: F. Müller | B16: 0.066666667 | C16: =IF(B16>0.3,"HIGH",IF(B16>0.15,"MEDIUM","LOW")) -> LOW
... A71: L. Okafor | B71: 0 | C71: =IF(B71>0.3,"HIGH",IF(B71>0.15,"MEDIUM","LOW")) -> LOW
A72: (blank) | C72: =IF(B72>0.3,"HIGH",IF(B72>0.15,"MEDIUM","LOW")) -> LOW
A73: (blank) | C73: =IF(B73>0.3,"HIGH",IF(B73>0.15,"MEDIUM","LOW")) -> LOW
A74: Grand Total | B74: 0.14240506 | C74: =IF(B74>0.3,"HIGH",IF(B74>0.15,"MEDIUM","LOW")) -> LOW

Sheet ORDERS PER MONTH
A3: Row Labels | B3: Count of OrderID
A4: Apr-2023 | B4: 24
A5: Apr-2024 | B5: 14
A6: Apr-2025 | B6: 25
A7: Aug-2023 | B7: 24
A8: Aug-2024 | B8: 20
A9: Aug-2025 | B9: 21
A10: Dec-2023 | B10: 21
A11: Dec-2024 | B11: 21
A12: Feb-2023 | B12: 17
A13: Feb-2024 | B13: 18
A14: Feb-2025 | B14: 16
A15: Jan-2023 | B15: 15
... A36: Sep-2025 | B36: 12
A37: (blank)
A38: Grand Total | B38: 632

Sheet Sheet2
A3: Row Labels | B3: Sum of GrossRevenue
A4: Sep-2024 | B4: 347613.19
A5: Grand Total | B5: 347613.19

Sheet Dashboard

Sheet Brief
A1: Assignment
A2: Excel Mastery Assignment: Sales Operations & Analytics
A4: Overview:
A5: You are an analyst for a multi-regional electronics distributor. The 'Data' sheet contains 632 rows and 15 columns of transactional data with intentional data-quality issues.
A6: Your job is to clean, enrich, analyze, and present insights via a dynamic dashboard.
A8: Part A — Data Cleaning & Preparation:
A9: 1) Create a staging table where you:
A10: • Remove exact duplicate rows (define and document your duplicate criteria).
A11: • Fix data types (dates as Dates, numeric fields as numbers).
A12: • Handle missing values for City, Salesperson, and Channel using reasonable business logic (document your approach).
A13: • Flag and correct suspicious UnitPrice values (e.g., negative prices) and discounts (e.g., > 30%).
A14: • Ensure RequiredDate is not earlier than OrderDate; where it is, impute a corrected RequiredDate (explain your rule).
... A67: 15) Ensure your dashboard responds to slicers without broken references.

Sheet Sheet1

Sheet Sheet3
A3: Row Labels | B3: Sum of GrossRevenue
A4: Sep-2024 | B4: 347613.19
A5: Grand Total | B5: 347613.19

Sheet Sheet4
A3: Sum of GrossProfit | B3: Column Labels
A4: Row Labels | B4: Direct | C4: Distributor | D4: Marketplace | E4: Online | F4: Retail | G4: Grand Total
A5: Africa | B5: 903.6836 | D5: 2404.4722 | F5: 6995.9311 | G5: 10304.087
A6: Americas | B6: 20607.028 | E6: 34086.703 | F6: 12346.561 | G6: 67040.292
A7: Asia | B7: 11819.496 | C7: 14529.414 | E7: 5307.8548 | G7: 31656.766
A8: Europe | D8: -5343.5468 | G8: -5343.5468
A9: Grand Total | B9: 33330.208 | C9: 14529.414 | D9: -2939.0746 | E9: 39394.557 | F9: 19342.492 | G9: 103657.6

Sheet Sheet6
A3: Row Labels | B3: Sum of GrossRevenue
A4: CMP-3093 | B4: 26015.449
A5: LAP-4483 | B5: 40563.322
A6: MON-6341 | B6: 31191.647
A7: NET-1145 | B7: 25249.613
A8: NET-9835 | B8: 20028.787
A9: PHN-4568 | B9: 42495.805
A10: PHN-8804 | B10: 37038.582
A11: PRN-2749 | B11: 28211.921
A12: PRN-6068 | B12: 15825.399
A13: PRN-9557 | B13: 21664.44
A14: Grand Total | B14: 288284.97

Sheet Sheet8
A3: Row Labels | B3: Average of Clean_DiscountPct
A4: CMP-3093 | B4: 0.051
A5: CMP-7563 | B5: 0.143
A6: LAP-4483 | B6: 0.163
A7: LAP-5150 | B7: 0.169
A8: MON-3504 | B8: 0.122
A9: MON-5249 | B9: 0.187
A10: MON-6341 | B10: 0.159
A11: NET-1145 | B11: 0.042
A12: NET-7998 | B12: 0.214
A13: NET-9835 | B13: 0.134
A14: PHN-4568 | B14: 0.021
A15: PHN-8804 | B15: 0.126
... A22: Grand Total | B22: 0.12972222

Sheet STORY TELLING
A1: Executive Sales Performance Insights
A3: Europe delivers the strongest overall performance, generating the highest gross profit relative to its sales volume. This suggests effective pricing strategies and strong cost control compared to other regions.
A4: The Americas contribute the largest share of total gross profit across all sales channels, with Direct and Online channels accounting for most of the region's profitability. This indicates a well-diversified sales strategy.
A5: Asia records moderate gross profit but trails behind the Americas. The region relies heavily on the Direct and Distributor channels, highlighting an opportunity to expand Marketplace and Retail sales.
A6: Africa has the lowest gross profit among the four regions, suggesting either lower sales volumes or limited market penetration. Increasing investment in high-performing channels could improve regional performance.
A7: Product revenue is concentrated in a few SKUs. The highest-performing products generate over 40,000 in revenue, while the lowest-performing products contribute less than 20,000, indicating that a small number of products drive a significant portion of sales.
A8: Discount levels vary considerably across products. Some SKUs receive discounts exceeding 25%, while others receive less than 5%. Evaluating whether these higher discounts translate into increased sales or reduced profitability could improve pricing decisions.

Sheet Sheet9
A1: Row Labels | B1: Average of Clean_DiscountPct
A2: CMP-3093 | B2: 0.051
A3: CMP-7563 | B3: 0.143
A4: LAP-4483 | B4: 0.163
A5: LAP-5150 | B5: 0.169
A6: MON-3504 | B6: 0.122
A7: MON-5249 | B7: 0.187
A8: MON-6341 | B8: 0.159
A9: NET-1145 | B9: 0.042
A10: NET-7998 | B10: 0.214
A11: NET-9835 | B11: 0.134
A12: PHN-4568 | B12: 0.021
A13: PHN-8804 | B13: 0.126
... A20: Grand Total | B20: 0.12972222

Sheet Data
A1: OrderID | B1: OrderDate | C1: OrderMonth | D1: OrderQuarter | E1: RequiredDate | F1: Date_Check | G1: LeadTimeDays | H1: CleanedRequiredDates | I1: Region | J1: RegionHierarchy | K1: Country_First SalesDate | L1: Country | M1: City | N1: CustomerSegment | O1: Channel | P1: Salesperson | Q1: ProductCategory | R1: SKU | S1: UnitCost | T1: UnitPrice | U1: UnitPrice_Tag | V1: Clean Unit Price | W1: PriceBand | X1: DiscountPct | Y1: Discount_Tag | Z1: Clean_DiscountPct | AA1: Quantity | AB1: GrossRevenue | AC1: CostofGoods | AD1: GrossProfit | AE1: MarginPct | AF1: OnTime_7Days | AG1: HighDiscount | AK1: ScenarioQty | AL1: ScenarioDiscount | AM1: ScenarioRevenue | AN1: ScenarioProfit
A2: ORD-2024-275203 | B2: 45362 | C2: =TEXT(B2,"mmm-yyyy") -> Mar-2024 | D2: ="Q" & ROUNDUP(MONTH(B2)/3,0) & "-" & YEAR(B2) -> Q1-2024 | E2: 45388 | F2: =IF(E2<B2,"Invalid RequiredDate","Valid") -> Valid | G2: =MEDIAN($E$2:$E$633-$B$2:$B$633) -> 26 | H2: =IF(E2<B2,B2+$G$2,E2) -> 45388 | I2: Africa | J2: =I2 & " → " & L2 & " → " & M2 -> Africa → Kenya → Kisumu | K2: =L2 & "-" & TEXT(C2,"YYYY-MM") -> Kenya-2024-03 | L2: Kenya | M2: Kisumu | N2: Corporate | O2: Retail | P2: C. Otieno | Q2: Components | R2: CMP-8270 | S2: 279.24 | T2: 608.9 | U2: =IF(T2<0,"Invalid Price","Valid") -> Valid | V2: =IF(T2<0,AVERAGEIF($Q$2:$Q$633,Q2,$T$2:$T$633),T2) -> 608.9 | W2: =IF(V2<=616.86,"Low",IF(V2<1912.05,"Medium","High")) -> Low | X2: 0.112 | Y2: =IF(X2>30%,"High Discount","Valid") -> Valid | Z2: =IF(X2>30%,30%,X2) -> 0.112 | AA2: 9 | AB2: =V2 * AA2 * (1 - Z2) -> 4866.3288 | AC2: =S2*AA2 -> 2513.16 | AD2: =AB2-AC2 -> 2353.1688 | AE2: =IF(AB2=0, 0, AD2 / AB2) -> 0.48356141 | AF2: =IF(G2<=7,1,0) -> 0 | AG2: =IF(Z2>20%,1,0) -> 0 | AK2: =AA2*(1+What_if_Analysis!$B$4) -> 10.8 | AL2: =MIN(Z2,What_if_Analysis!$B$2) -> 0.05 | AM2: =AK2*V2*(1-AL2) -> 6247.314 | AN2: =AM2-(AK2*(T2*(1+What_if_Analysis!$B$3))) -> -986.418
A3: ORD-2024-358795 | B3: 45588 | C3: =TEXT(B3,"mmm-yyyy") -> Oct-2024 | D3: ="Q" & ROUNDUP(MONTH(B3)/3,0) & "-" & YEAR(B3) -> Q4-2024 | E3: 45587 | F3: =IF(E3<B3,"Invalid RequiredDate","Valid") -> Invalid RequiredDate | G3: =MEDIAN($E$2:$E$633-$B$2:$B$633) -> -1 | H3: =IF(E3<B3,B3+$G$2,E3) -> 45614 | I3: Africa | J3: =I3 & " → " & L3 & " → " & M3 -> Africa → Nigeria → Port Harcourt | K3: =L3 & "-" & TEXT(C3,"YYYY-MM") -> Nigeria-2024-10 | L3: Nigeria | M3: Port Harcourt | N3: Education | O3: Online | P3: J. Njeri | Q3: Printers | R3: PRN-9322 | S3: 1084.39 | T3: 759.33 | U3: =IF(T3<0,"Invalid Price","Valid") -> Valid | V3: =IF(T3<0,AVERAGEIF($Q$2:$Q$633,Q3,$T$2:$T$633),T3) -> 759.33 | W3: =IF(V3<=616.86,"Low",IF(V3<1912.05,"Medium","High")) -> Medium | X3: 0.237 | Y3: =IF(X3>30%,"High Discount","Valid") -> Valid | Z3: =IF(X3>30%,30%,X3) -> 0.237 | AA3: 31 | AB3: =V3 * AA3 * (1 - Z3) -> 17960.432 | AC3: =S3*AA3 -> 33616.09 | AD3: =AB3-AC3 -> -15655.658 | AE3: =IF(AB3=0, 0, AD3 / AB3) -> -0.87167486 | AF3: =IF(G3<=7,1,0) -> 1 | AG3: =IF(Z3>20%,1,0) -> 1 | AK3: =AA3*(1+What_if_Analysis!$B$4) -> 37.2 | AL3: =MIN(Z3,What_if_Analysis!$B$2) -> 0.05 | AM3: =AK3*V3*(1-AL3) -> 26834.722 | AN3: =AM3-(AK3*(T3*(1+What_if_Analysis!$B$3))) -> -4237.0614
A4: ORD-2023-373538 | B4: 44985 | C4: =TEXT(B4,"mmm-yyyy") -> Feb-2023 | D4: ="Q" & ROUNDUP(MONTH(B4)/3,0) & "-" & YEAR(B4) -> Q1-2023 | E4: 45010 | F4: =IF(E4<B4,"Invalid RequiredDate","Valid") -> Valid | G4: =MEDIAN($E$2:$E$633-$B$2:$B$633) -> 25 | H4: =IF(E4<B4,B4+$G$2,E4) -> 45010 | I4: Africa | J4: =I4 & " → " & L4 & " → " & M4 -> Africa → Kenya → Nairobi | K4: =L4 & "-" & TEXT(C4,"YYYY-MM") -> Kenya-2023-02 | L4: Kenya | M4: Nairobi | N4: Corporate | O4: Retail | P4: I. Johnson | Q4: Networking | R4: NET-9666 | S4: 1460.76 | T4: -30.66 | U4: =IF(T4<0,"Invalid Price","Valid") -> Invalid Price | V4: =IF(T4<0,AVERAGEIF($Q$2:$Q$633,Q4,$T$2:$T$633),T4) -> 1445.2723 | W4: =IF(V4<=616.86,"Low",IF(V4<1912.05,"Medium","High")) -> Medium | X4: 0.131 | Y4: =IF(X4>30%,"High Discount","Valid") -> Valid | Z4: =IF(X4>30%,30%,X4) -> 0.131 | AA4: 12 | AB4: =V4 * AA4 * (1 - Z4) -> 15071.3 | AC4: =S4*AA4 -> 17529.12 | AD4: =AB4-AC4 -> -2457.8202 | AE4: =IF(AB4=0, 0, AD4 / AB4) -> -0.16307951 | AF4: =IF(G4<=7,1,0) -> 0 | AG4: =IF(Z4>20%,1,0) -> 0 | AK4: =AA4*(1+What_if_Analysis!$B$4) -> 14.4 | AL4: =MIN(Z4,What_if_Analysis!$B$2) -> 0.05 | AM4: =AK4*V4*(1-AL4) -> 19771.325 | AN4: =AM4-(AK4*(T4*(1+What_if_Analysis!$B$3))) -> 20256.98
A5: ORD-2025-168148 | B5: 45745 | C5: =TEXT(B5,"mmm-yyyy") -> Mar-2025 | D5: ="Q" & ROUNDUP(MONTH(B5)/3,0) & "-" & YEAR(B5) -> Q1-2025 | E5: 45749 | F5: =IF(E5<B5,"Invalid RequiredDate","Valid") -> Valid | G5: =MEDIAN($E$2:$E$633-$B$2:$B$633) -> 4 | H5: =IF(E5<B5,B5+$G$2,E5) -> 45749 | I5: Africa | J5: =I5 & " → " & L5 & " → " & M5 -> Africa → Nigeria → Lagos | K5: =L5 & "-" & TEXT(C5,"YYYY-MM") -> Nigeria-2025-03 | L5: Nigeria | M5: Lagos | N5: Non-Profit | O5: Marketplace | P5: G. Dubois | Q5: Phones | R5: PHN-4556 | S5: 259.93 | T5: 255.94 | U5: =IF(T5<0,"Invalid Price","Valid") -> Valid | V5: =IF(T5<0,AVERAGEIF($Q$2:$Q$633,Q5,$T$2:$T$633),T5) -> 255.94 | W5: =IF(V5<=616.86,"Low",IF(V5<1912.05,"Medium","High")) -> Low | X5: 0.072 | Y5: =IF(X5>30%,"High Discount","Valid") -> Valid | Z5: =IF(X5>30%,30%,X5) -> 0.072 | AA5: 22 | AB5: =V5 * AA5 * (1 - Z5) -> 5225.271 | AC5: =S5*AA5 -> 5718.46 | AD5: =AB5-AC5 -> -493.18896 | AE5: =IF(AB5=0, 0, AD5 / AB5) -> -0.094385335 | AF5: =IF(G5<=7,1,0) -> 1 | AG5: =IF(Z5>20%,1,0) -> 0 | AK5: =AA5*(1+What_if_Analysis!$B$4) -> 26.4 | AL5: =MIN(Z5,What_if_Analysis!$B$2) -> 0.05 | AM5: =AK5*V5*(1-AL5) -> 6418.9752 | AN5: =AM5-(AK5*(T5*(1+What_if_Analysis!$B$3))) -> -1013.5224
A6: ORD-2023-824839 | B6: 45266 | C6: =TEXT(B6,"mmm-yyyy") -> Dec-2023 | D6: ="Q" & ROUNDUP(MONTH(B6)/3,0) & "-" & YEAR(B6) -> Q4-2023 | E6: 45291 | F6: =IF(E6<B6,"Invalid RequiredDate","Valid") -> Valid | G6: =MEDIAN($E$2:$E$633-$B$2:$B$633) -> 25 | H6: =IF(E6<B6,B6+$G$2,E6) -> 45291 | I6: Asia | J6: =I6 & " → " & L6 & " → " & M6 -> Asia → Japan → Osaka | K6: =L6 & "-" & TEXT(C6,"YYYY-MM") -> Japan-2023-12 | L6: Japan | M6: Osaka | N6: Consumer | O6: Retail | P6: L. Okafor | Q6: Printers | R6: PRN-8041 | S6: 663.03 | T6: 813.51 | U6: =IF(T6<0,"Invalid Price","Valid") -> Valid | V6: =IF(T6<0,AVERAGEIF($Q$2:$Q$633,Q6,$T$2:$T$633),T6) -> 813.51 | W6: =IF(V6<=616.86,"Low",IF(V6<1912.05,"Medium","High")) -> Medium | X6: 0.102 | Y6: =IF(X6>30%,"High Discount","Valid") -> Valid | Z6: =IF(X6>30%,30%,X6) -> 0.102 | AA6: 15 | AB6: =V6 * AA6 * (1 - Z6) -> 10957.98 | AC6: =S6*AA6 -> 9945.45 | AD6: =AB6-AC6 -> 1012.5297 | AE6: =IF(AB6=0, 0, AD6 / AB6) -> 0.092401129 | AF6: =IF(G6<=7,1,0) -> 0 | AG6: =IF(Z6>20%,1,0) -> 0 | AK6: =AA6*(1+What_if_Analysis!$B$4) -> 18 | AL6: =MIN(Z6,What_if_Analysis!$B$2) -> 0.05 | AM6: =AK6*V6*(1-AL6) -> 13911.021 | AN6: =AM6-(AK6*(T6*(1+What_if_Analysis!$B$3))) -> -2196.477
A7: ORD-2023-723587 | B7: 44928 | C7: =TEXT(B7,"mmm-yyyy") -> Jan-2023 | D7: ="Q" & ROUNDUP(MONTH(B7)/3,0) & "-" & YEAR(B7) -> Q1-2023 | E7: 44931 | F7: =IF(E7<B7,"Invalid RequiredDate","Valid") -> Valid | G7: =MEDIAN($E$2:$E$633-$B$2:$B$633) -> 3 | H7: =IF(E7<B7,B7+$G$2,E7) -> 44931 | I7: Americas | J7: =I7 & " → " & L7 & " → " & M7 -> Americas → Canada → Toronto | K7: =L7 & "-" & TEXT(C7,"YYYY-MM") -> Canada-2023-01 | L7: Canada | M7: Toronto | N7: Corporate | O7: Distributor | P7: B. Chen | Q7: Laptops | R7: LAP-8555 | S7: 315.87 | T7: 591.68 | U7: =IF(T7<0,"Invalid Price","Valid") -> Valid | V7: =IF(T7<0,AVERAGEIF($Q$2:$Q$633,Q7,$T$2:$T$633),T7) -> 591.68 | W7: =IF(V7<=616.86,"Low",IF(V7<1912.05,"Medium","High")) -> Low | X7: 0 | Y7: =IF(X7>30%,"High Discount","Valid") -> Valid | Z7: =IF(X7>30%,30%,X7) -> 0 | AA7: 7 | AB7: =V7 * AA7 * (1 - Z7) -> 4141.76 | AC7: =S7*AA7 -> 2211.09 | AD7: =AB7-AC7 -> 1930.67 | AE7: =IF(AB7=0, 0, AD7 / AB7) -> 0.46614724 | AF7: =IF(G7<=7,1,0) -> 1 | AG7: =IF(Z7>20%,1,0) -> 0 | AK7: =AA7*(1+What_if_Analysis!$B$4) -> 8.4 | AL7: =MIN(Z7,What_if_Analysis!$B$2) -> 0 | AM7: =AK7*V7*(1-AL7) -> 4970.112 | AN7: =AM7-(AK7*(T7*(1+What_if_Analysis!$B$3))) -> -497.0112
A8: ORD-2024-336584 | B8: 45653 | C8: =TEXT(B8,"mmm-yyyy") -> Dec-2024 | D8: ="Q" & ROUNDUP(MONTH(B8)/3,0) & "-" & YEAR(B8) -> Q4-2024 | E8: 45671 | F8: =IF(E8<B8,"Invalid RequiredDate","Valid") -> Valid | G8: =MEDIAN($E$2:$E$633-$B$2:$B$633) -> 18 | H8: =IF(E8<B8,B8+$G$2,E8) -> 45671 | I8: Asia | J8: =I8 & " → " & L8 & " → " & M8 -> Asia → India → Bengaluru | K8: =L8 & "-" & TEXT(C8,"YYYY-MM") -> India-2024-12 | L8: India | M8: Bengaluru | N8: Small Business | O8: Marketplace | P8: E. Garcia | Q8: Monitors | R8: MON-8629 | S8: 586.07 | T8: 845.97 | U8: =IF(T8<0,"Invalid Price","Valid") -> Valid | V8: =IF(T8<0,AVERAGEIF($Q$2:$Q$633,Q8,$T$2:$T$633),T8) -> 845.97 | W8: =IF(V8<=616.86,"Low",IF(V8<1912.05,"Medium","High")) -> Medium | X8: 0.147 | Y8: =IF(X8>30%,"High Discount","Valid") -> Valid | Z8: =IF(X8>30%,30%,X8) -> 0.147 | AA8: 4 | AB8: =V8 * AA8 * (1 - Z8) -> 2886.4496 | AC8: =S8*AA8 -> 2344.28 | AD8: =AB8-AC8 -> 542.16964 | AE8: =IF(AB8=0, 0, AD8 / AB8) -> 0.1878327 | AF8: =IF(G8<=7,1,0) -> 0 | AG8: =IF(Z8>20%,1,0) -> 0 | AK8: =AA8*(1+What_if_Analysis!$B$4) -> 4.8 | AL8: =MIN(Z8,What_if_Analysis!$B$2) -> 0.05 | AM8: =AK8*V8*(1-AL8) -> 3857.6232 | AN8: =AM8-(AK8*(T8*(1+What_if_Analysis!$B$3))) -> -609.0984
A9: ORD-2023-112666 | B9: 44941 | C9: =TEXT(B9,"mmm-yyyy") -> Jan-2023 | D9: ="Q" & ROUNDUP(MONTH(B9)/3,0) & "-" & YEAR(B9) -> Q1-2023 | E9: 44939 | F9: =IF(E9<B9,"Invalid RequiredDate","Valid") -> Invalid RequiredDate | G9: =MEDIAN($E$2:$E$633-$B$2:$B$633) -> -2 | H9: =IF(E9<B9,B9+$G$2,E9) -> 44967 | I9: Africa | J9: =I9 & " → " & L9 & " → " & M9 -> Africa → Nigeria → Abuja | K9: =L9 & "-" & TEXT(C9,"YYYY-MM") -> Nigeria-2023-01 | L9: Nigeria | M9: Abuja | N9: Education | O9: Online | P9: O. Wang | Q9: Printers | R9: PRN-6276 | S9: 28.38 | T9: 47.22 | U9: =IF(T9<0,"Invalid Price","Valid") -> Valid | V9: =IF(T9<0,AVERAGEIF($Q$2:$Q$633,Q9,$T$2:$T$633),T9) -> 47.22 | W9: =IF(V9<=616.86,"Low",IF(V9<1912.05,"Medium","High")) -> Low | X9: 0.194 | Y9: =IF(X9>30%,"High Discount","Valid") -> Valid | Z9: =IF(X9>30%,30%,X9) -> 0.194 | AA9: 18 | AB9: =V9 * AA9 * (1 - Z9) -> 685.06776 | AC9: =S9*AA9 -> 510.84 | AD9: =AB9-AC9 -> 174.22776 | AE9: =IF(AB9=0, 0, AD9 / AB9) -> 0.25432194 | AF9: =IF(G9<=7,1,0) -> 1 | AG9: =IF(Z9>20%,1,0) -> 0 | AK9: =AA9*(1+What_if_Analysis!$B$4) -> 21.6 | AL9: =MIN(Z9,What_if_Analysis!$B$2) -> 0.05 | AM9: =AK9*V9*(1-AL9) -> 968.9544 | AN9: =AM9-(AK9*(T9*(1+What_if_Analysis!$B$3))) -> -152.9928
A10: ORD-2024-589570 | B10: 45416 | C10: =TEXT(B10,"mmm-yyyy") -> May-2024 | D10: ="Q" & ROUNDUP(MONTH(B10)/3,0) & "-" & YEAR(B10) -> Q2-2024 | E10: 45441 | F10: =IF(E10<B10,"Invalid RequiredDate","Valid") -> Valid | G10: =MEDIAN($E$2:$E$633-$B$2:$B$633) -> 25 | H10: =IF(E10<B10,B10+$G$2,E10) -> 45441 | I10: Africa | J10: =I10 & " → " & L10 & " → " & M10 -> Africa → Nigeria → Abuja | K10: =L10 & "-" & TEXT(C10,"YYYY-MM") -> Nigeria-2024-05 | L10: Nigeria | M10: Abuja | N10: Non-Profit | O10: Marketplace | P10: O. Wang | Q10: Monitors | R10: MON-6892 | S10: 1295.34 | T10: 2530.81 | U10: =IF(T10<0,"Invalid Price","Valid") -> Valid | V10: =IF(T10<0,AVERAGEIF($Q$2:$Q$633,Q10,$T$2:$T$633),T10) -> 2530.81 | W10: =IF(V10<=616.86,"Low",IF(V10<1912.05,"Medium","High")) -> High | X10: 0.031 | Y10: =IF(X10>30%,"High Discount","Valid") -> Valid | Z10: =IF(X10>30%,30%,X10) -> 0.031 | AA10: 6 | AB10: =V10 * AA10 * (1 - Z10) -> 14714.129 | AC10: =S10*AA10 -> 7772.04 | AD10: =AB10-AC10 -> 6942.0893 | AE10: =IF(AB10=0, 0, AD10 / AB10) -> 0.47179749 | AF10: =IF(G10<=7,1,0) -> 0 | AG10: =IF(Z10>20%,1,0) -> 0 | AK10: =AA10*(1+What_if_Analysis!$B$4) -> 7.2 | AL10: =MIN(Z10,What_if_Analysis!$B$2) -> 0.031 | AM10: =AK10*V10*(1-AL10) -> 17656.955 | AN10: =AM10-(AK10*(T10*(1+What_if_Analysis!$B$3))) -> -2387.06
A11: ORD-2025-997421 | B11: 45798 | C11: =TEXT(B11,"mmm-yyyy") -> May-2025 | D11: ="Q" & ROUNDUP(MONTH(B11)/3,0) & "-" & YEAR(B11) -> Q2-2025 | E11: 45817 | F11: =IF(E11<B11,"Invalid RequiredDate","Valid") -> Valid | G11: =MEDIAN($E$2:$E$633-$B$2:$B$633) -> 19 | H11: =IF(E11<B11,B11+$G$2,E11) -> 45817 | I11: Americas | J11: =I11 & " → " & L11 & " → " & M11 -> Americas → Brazil → São Paulo | K11: =L11 & "-" & TEXT(C11,"YYYY-MM") -> Brazil-2025-05 | L11: Brazil | M11: São Paulo | N11: Non-Profit | O11: Online | P11: A. Patel | Q11: Components | R11: CMP-3731 | S11: 1331.38 | T11: 2309.56 | U11: =IF(T11<0,"Invalid Price","Valid") -> Valid | V11: =IF(T11<0,AVERAGEIF($Q$2:$Q$633,Q11,$T$2:$T$633),T11) -> 2309.56 | W11: =IF(V11<=616.86,"Low",IF(V11<1912.05,"Medium","High")) -> High | X11: 0.149 | Y11: =IF(X11>30%,"High Discount","Valid") -> Valid | Z11: =IF(X11>30%,30%,X11) -> 0.149 | AA11: 31 | AB11: =V11 * AA11 * (1 - Z11) -> 60928.502 | AC11: =S11*AA11 -> 41272.78 | AD11: =AB11-AC11 -> 19655.722 | AE11: =IF(AB11=0, 0, AD11 / AB11) -> 0.32260308 | AF11: =IF(G11<=7,1,0) -> 0 | AG11: =IF(Z11>20%,1,0) -> 0 | AK11: =AA11*(1+What_if_Analysis!$B$4) -> 37.2 | AL11: =MIN(Z11,What_if_Analysis!$B$2) -> 0.05 | AM11: =AK11*V11*(1-AL11) -> 81619.85 | AN11: =AM11-(AK11*(T11*(1+What_if_Analysis!$B$3))) -> -12887.345
A12: ORD-2024-210687 | B12: 45319 | C12: =TEXT(B12,"mmm-yyyy") -> Jan-2024 | D12: ="Q" & ROUNDUP(MONTH(B12)/3,0) & "-" & YEAR(B12) -> Q1-2024 | E12: 45331 | F12: =IF(E12<B12,"Invalid RequiredDate","Valid") -> Valid | G12: =MEDIAN($E$2:$E$633-$B$2:$B$633) -> 12 | H12: =IF(E12<B12,B12+$G$2,E12) -> 45331 | I12: Europe | J12: =I12 & " → " & L12 & " → " & M12 -> Europe → Germany → Berlin | K12: =L12 & "-" & TEXT(C12,"YYYY-MM") -> Germany-2024-01 | L12: Germany | M12: Berlin | N12: Corporate | O12: Online | P12: G. Dubois | Q12: Accessories | R12: ACC-7938 | S12: 644.17 | T12: 700.12 | U12: =IF(T12<0,"Invalid Price","Valid") -> Valid | V12: =IF(T12<0,AVERAGEIF($Q$2:$Q$633,Q12,$T$2:$T$633),T12) -> 700.12 | W12: =IF(V12<=616.86,"Low",IF(V12<1912.05,"Medium","High")) -> Medium | X12: 0.006 | Y12: =IF(X12>30%,"High Discount","Valid") -> Valid | Z12: =IF(X12>30%,30%,X12) -> 0.006 | AA12: 23 | AB12: =V12 * AA12 * (1 - Z12) -> 16006.143 | AC12: =S12*AA12 -> 14815.91 | AD12: =AB12-AC12 -> 1190.2334 | AE12: =IF(AB12=0, 0, AD12 / AB12) -> 0.074361038 | AF12: =IF(G12<=7,1,0) -> 0 | AG12: =IF(Z12>20%,1,0) -> 0 | AK12: =AA12*(1+What_if_Analysis!$B$4) -> 27.6 | AL12: =MIN(Z12,What_if_Analysis!$B$2) -> 0.006 | AM12: =AK12*V12*(1-AL12) -> 19207.372 | AN12: =AM12-(AK12*(T12*(1+What_if_Analysis!$B$3))) -> -2048.2711
A13: ORD-2025-515515 | B13: 45660 | C13: =TEXT(B13,"mmm-yyyy") -> Jan-2025 | D13: ="Q" & ROUNDUP(MONTH(B13)/3,0) & "-" & YEAR(B13) -> Q1-2025 | E13: 45680 | F13: =IF(E13<B13,"Invalid RequiredDate","Valid") -> Valid | G13: =MEDIAN($E$2:$E$633-$B$2:$B$633) -> 20 | H13: =IF(E13<B13,B13+$G$2,E13) -> 45680 | I13: Asia | J13: =I13 & " → " & L13 & " → " & M13 -> Asia → Japan → Osaka | K13: =L13 & "-" & TEXT(C13,"YYYY-MM") -> Japan-2025-01 | L13: Japan | M13: Osaka | N13: Corporate | O13: Distributor | P13: F. Müller | Q13: Phones | R13: PHN-7019 | S13: 908.6 | T13: 691.37 | U13: =IF(T13<0,"Invalid Price","Valid") -> Valid | V13: =IF(T13<0,AVERAGEIF($Q$2:$Q$633,Q13,$T$2:$T$633),T13) -> 691.37 | W13: =IF(V13<=616.86,"Low",IF(V13<1912.05,"Medium","High")) -> Medium | X13: 0.25 | Y13: =IF(X13>30%,"High Discount","Valid") -> Valid | Z13: =IF(X13>30%,30%,X13) -> 0.25 | AA13: 20 | AB13: =V13 * AA13 * (1 - Z13) -> 10370.55 | AC13: =S13*AA13 -> 18172 | AD13: =AB13-AC13 -> -7801.45 | AE13: =IF(AB13=0, 0, AD13 / AB13) -> -0.75226965 | AF13: =IF(G13<=7,1,0) -> 0 | AG13: =IF(Z13>20%,1,0) -> 1 | AH13: QUARTILES | AK13: =AA13*(1+What_if_Analysis!$B$4) -> 24 | AL13: =MIN(Z13,What_if_Analysis!$B$2) -> 0.05 | AM13: =AK13*V13*(1-AL13) -> 15763.236 | AN13: =AM13-(AK13*(T13*(1+What_if_Analysis!$B$3))) -> -2488.932
A14: ORD-2025-487261 | B14: 45722 | C14: =TEXT(B14,"mmm-yyyy") -> Mar-2025 | D14: ="Q" & ROUNDUP(MONTH(B14)/3,0) & "-" & YEAR(B14) -> Q1-2025 | E14: 45747 | F14: =IF(E14<B14,"Invalid RequiredDate","Valid") -> Valid | G14: =MEDIAN($E$2:$E$633-$B$2:$B$633) -> 25 | H14: =IF(E14<B14,B14+$G$2,E14) -> 45747 | I14: Americas | J14: =I14 & " → " & L14 & " → " & M14 -> Americas → Brazil → Brasília | K14: =L14 & "-" & TEXT(C14,"YYYY-MM") -> Brazil-2025-03 | L14: Brazil | M14: Brasília | N14: Non-Profit | O14: Online | P14: J. Njeri | Q14: Components | R14: CMP-3693 | S14: 331.57 | T14: 548.4 | U14: =IF(T14<0,"Invalid Price","Valid") -> Valid | V14: =IF(T14<0,AVERAGEIF($Q$2:$Q$633,Q14,$T$2:$T$633),T14) -> 548.4 | W14: =IF(V14<=616.86,"Low",IF(V14<1912.05,"Medium","High")) -> Low | X14: 0.094 | Y14: =IF(X14>30%,"High Discount","Valid") -> Valid | Z14: =IF(X14>30%,30%,X14) -> 0.094 | AA14: 10 | AB14: =V14 * AA14 * (1 - Z14) -> 4968.504 | AC14: =S14*AA14 -> 3315.7 | AD14: =AB14-AC14 -> 1652.804 | AE14: =IF(AB14=0, 0, AD14 / AB14) -> 0.33265627 | AF14: =IF(G14<=7,1,0) -> 0 | AG14: =IF(Z14>20%,1,0) -> 0 | AH14: =_xlfn.QUARTILE.INC(V:V,1) -> 616.8575 | AK14: =AA14*(1+What_if_Analysis!$B$4) -> 12 | AL14: =MIN(Z14,What_if_Analysis!$B$2) -> 0.05 | AM14: =AK14*V14*(1-AL14) -> 6251.76 | AN14: =AM14-(AK14*(T14*(1+What_if_Analysis!$B$3))) -> -987.12
A15: ORD-2024-890180 | B15: 45311 | C15: =TEXT(B15,"mmm-yyyy") -> Jan-2024 | D15: ="Q" & ROUNDUP(MONTH(B15)/3,0) & "-" & YEAR(B15) -> Q1-2024 | E15: 45335 | F15: =IF(E15<B15,"Invalid RequiredDate","Valid") -> Valid | G15: =MEDIAN($E$2:$E$633-$B$2:$B$633) -> 24 | H15: =IF(E15<B15,B15+$G$2,E15) -> 45335 | I15: Europe | J15: =I15 & " → " & L15 & " → " & M15 -> Europe → France → Marseille | K15: =L15 & "-" & TEXT(C15,"YYYY-MM") -> France-2024-01 | L15: France | M15: Marseille | N15: Corporate | O15: Retail | P15: H. Kim | Q15: Printers | R15: PRN-8392 | S15: 643.53 | T15: 1439.01 | U15: =IF(T15<0,"Invalid Price","Valid") -> Valid | V15: =IF(T15<0,AVERAGEIF($Q$2:$Q$633,Q15,$T$2:$T$633),T15) -> 1439.01 | W15: =IF(V15<=616.86,"Low",IF(V15<1912.05,"Medium","High")) -> Medium | X15: 0 | Y15: =IF(X15>30%,"High Discount","Valid") -> Valid | Z15: =IF(X15>30%,30%,X15) -> 0 | AA15: 15 | AB15: =V15 * AA15 * (1 - Z15) -> 21585.15 | AC15: =S15*AA15 -> 9652.95 | AD15: =AB15-AC15 -> 11932.2 | AE15: =IF(AB15=0, 0, AD15 / AB15) -> 0.55279671 | AF15: =IF(G15<=7,1,0) -> 0 | AG15: =IF(Z15>20%,1,0) -> 0 | AH15: =_xlfn.QUARTILE.INC(V:V,2) -> 1208.04 | AK15: =AA15*(1+What_if_Analysis!$B$4) -> 18 | AL15: =MIN(Z15,What_if_Analysis!$B$2) -> 0 | AM15: =AK15*V15*(1-AL15) -> 25902.18 | AN15: =AM15-(AK15*(T15*(1+What_if_Analysis!$B$3))) -> -2590.218
A16: ORD-2025-840976 | B16: 45901 | C16: =TEXT(B16,"mmm-yyyy") -> Sept-2025 | D16: ="Q" & ROUNDUP(MONTH(B16)/3,0) & "-" & YEAR(B16) -> Q3-2025 | E16: 45930 | F16: =IF(E16<B16,"Invalid RequiredDate","Valid") -> Valid | G16: =MEDIAN($E$2:$E$633-$B$2:$B$633) -> 29 | H16: =IF(E16<B16,B16+$G$2,E16) -> 45930 | I16: Americas | J16: =I16 & " → " & L16 & " → " & M16 -> Americas → Brazil → Brasília | K16: =L16 & "-" & TEXT(C16,"YYYY-MM") -> Brazil-2025-09 | L16: Brazil | M16: Brasília | N16: Education | O16: Retail | P16: K. Singh | Q16: Accessories | R16: ACC-1663 | S16: 780.59 | T16: 631.57 | U16: =IF(T16<0,"Invalid Price","Valid") -> Valid | V16: =IF(T16<0,AVERAGEIF($Q$2:$Q$633,Q16,$T$2:$T$633),T16) -> 631.57 | W16: =IF(V16<=616.86,"Low",IF(V16<1912.05,"Medium","High")) -> Medium | X16: 0 | Y16: =IF(X16>30%,"High Discount","Valid") -> Valid | Z16: =IF(X16>30%,30%,X16) -> 0 | AA16: 12 | AB16: =V16 * AA16 * (1 - Z16) -> 7578.84 | AC16: =S16*AA16 -> 9367.08 | AD16: =AB16-AC16 -> -1788.24 | AE16: =IF(AB16=0, 0, AD16 / AB16) -> -0.23595168 | AF16: =IF(G16<=7,1,0) -> 0 | AG16: =IF(Z16>20%,1,0) -> 0 | AH16: =_xlfn.QUARTILE.INC(V:V,3) -> 1912.045 | AK16: =AA16*(1+What_if_Analysis!$B$4) -> 14.4 | AL16: =MIN(Z16,What_if_Analysis!$B$2) -> 0 | AM16: =AK16*V16*(1-AL16) -> 9094.608 | AN16: =AM16-(AK16*(T16*(1+What_if_Analysis!$B$3))) -> -909.4608
A17: ORD-2023-937291 | B17: 45039 | C17: =TEXT(B17,"mmm-yyyy") -> Apr-2023 | D17: ="Q" & ROUNDUP(MONTH(B17)/3,0) & "-" & YEAR(B17) -> Q2-2023 | E17: 45038 | F17: =IF(E17<B17,"Invalid RequiredDate","Valid") -> Invalid RequiredDate | G17: =MEDIAN($E$2:$E$633-$B$2:$B$633) -> -1 | H17: =IF(E17<B17,B17+$G$2,E17) -> 45065 | I17: Africa | J17: =I17 & " → " & L17 & " → " & M17 -> Africa → Kenya → Nairobi | K17: =L17 & "-" & TEXT(C17,"YYYY-MM") -> Kenya-2023-04 | L17: Kenya | M17: Nairobi | N17: Small Business | O17: Direct | P17: E. Garcia | Q17: Laptops | R17: LAP-1698 | S17: 756.51 | T17: 850.8 | U17: =IF(T17<0,"Invalid Price","Valid") -> Valid | V17: =IF(T17<0,AVERAGEIF($Q$2:$Q$633,Q17,$T$2:$T$633),T17) -> 850.8 | W17: =IF(V17<=616.86,"Low",IF(V17<1912.05,"Medium","High")) -> Medium | X17: 0.074 | Y17: =IF(X17>30%,"High Discount","Valid") -> Valid | Z17: =IF(X17>30%,30%,X17) -> 0.074 | AA17: 9 | AB17: =V17 * AA17 * (1 - Z17) -> 7090.5672 | AC17: =S17*AA17 -> 6808.59 | AD17: =AB17-AC17 -> 281.9772 | AE17: =IF(AB17=0, 0, AD17 / AB17) -> 0.039767933 | AF17: =IF(G17<=7,1,0) -> 1 | AG17: =IF(Z17>20%,1,0) -> 0 | AK17: =AA17*(1+What_if_Analysis!$B$4) -> 10.8 | AL17: =MIN(Z17,What_if_Analysis!$B$2) -> 0.05 | AM17: =AK17*V17*(1-AL17) -> 8729.208 | AN17: =AM17-(AK17*(T17*(1+What_if_Analysis!$B$3))) -> -1378.296
A18: ORD-2024-206081 | B18: 45636 | C18: =TEXT(B18,"mmm-yyyy") -> Dec-2024 | D18: ="Q" & ROUNDUP(MONTH(B18)/3,0) & "-" & YEAR(B18) -> Q4-2024 | E18: 45665 | F18: =IF(E18<B18,"Invalid RequiredDate","Valid") -> Valid | G18: =MEDIAN($E$2:$E$633-$B$2:$B$633) -> 29 | H18: =IF(E18<B18,B18+$G$2,E18) -> 45665 | I18: Europe | J18: =I18 & " → " & L18 & " → " & M18 -> Europe → France → Marseille | K18: =L18 & "-" & TEXT(C18,"YYYY-MM") -> France-2024-12 | L18: France | M18: Marseille | N18: Small Business | O18: Retail | P18: K. Singh | Q18: Printers | R18: PRN-6791 | S18: 891.08 | T18: 1040.1 | U18: =IF(T18<0,"Invalid Price","Valid") -> Valid | V18: =IF(T18<0,AVERAGEIF($Q$2:$Q$633,Q18,$T$2:$T$633),T18) -> 1040.1 | W18: =IF(V18<=616.86,"Low",IF(V18<1912.05,"Medium","High")) -> Medium | X18: 0.109 | Y18: =IF(X18>30%,"High Discount","Valid") -> Valid | Z18: =IF(X18>30%,30%,X18) -> 0.109 | AA18: 28 | AB18: =V18 * AA18 * (1 - Z18) -> 25948.415 | AC18: =S18*AA18 -> 24950.24 | AD18: =AB18-AC18 -> 998.1748 | AE18: =IF(AB18=0, 0, AD18 / AB18) -> 0.03846766 | AF18: =IF(G18<=7,1,0) -> 0 | AG18: =IF(Z18>20%,1,0) -> 0 | AK18: =AA18*(1+What_if_Analysis!$B$4) -> 33.6 | AL18: =MIN(Z18,What_if_Analysis!$B$2) -> 0.05 | AM18: =AK18*V18*(1-AL18) -> 33199.992 | AN18: =AM18-(AK18*(T18*(1+What_if_Analysis!$B$3))) -> -5242.104
A19: ORD-2025-233883 | B19: 45908 | C19: =TEXT(B19,"mmm-yyyy") -> Sept-2025 | D19: ="Q" & ROUNDUP(MONTH(B19)/3,0) & "-" & YEAR(B19) -> Q3-2025 | E19: 45916 | F19: =IF(E19<B19,"Invalid RequiredDate","Valid") -> Valid | G19: =MEDIAN($E$2:$E$633-$B$2:$B$633) -> 8 | H19: =IF(E19<B19,B19+$G$2,E19) -> 45916 | I19: Asia | J19: =I19 & " → " & L19 & " → " & M19 -> Asia → Japan → Osaka | K19: =L19 & "-" & TEXT(C19,"YYYY-MM") -> Japan-2025-09 | L19: Japan | M19: Osaka | N19: Corporate | O19: Distributor | P19: C. Otieno | Q19: Phones | R19: PHN-1197 | S19: 1225.57 | T19: 2705.57 | U19: =IF(T19<0,"Invalid Price","Valid") -> Valid | V19: =IF(T19<0,AVERAGEIF($Q$2:$Q$633,Q19,$T$2:$T$633),T19) -> 2705.57 | W19: =IF(V19<=616.86,"Low",IF(V19<1912.05,"Medium","High")) -> High | X19: 0.183 | Y19: =IF(X19>30%,"High Discount","Valid") -> Valid | Z19: =IF(X19>30%,30%,X19) -> 0.183 | AA19: 16 | AB19: =V19 * AA19 * (1 - Z19) -> 35367.211 | AC19: =S19*AA19 -> 19609.12 | AD19: =AB19-AC19 -> 15758.091 | AE19: =IF(AB19=0, 0, AD19 / AB19) -> 0.44555651 | AF19: =IF(G19<=7,1,0) -> 0 | AG19: =IF(Z19>20%,1,0) -> 0 | AK19: =AA19*(1+What_if_Analysis!$B$4) -> 19.2 | AL19: =MIN(Z19,What_if_Analysis!$B$2) -> 0.05 | AM19: =AK19*V19*(1-AL19) -> 49349.597 | AN19: =AM19-(AK19*(T19*(1+What_if_Analysis!$B$3))) -> -7792.0416
A20: ORD-2025-843974 | B20: 45858 | C20: =TEXT(B20,"mmm-yyyy") -> Jul-2025 | D20: ="Q" & ROUNDUP(MONTH(B20)/3,0) & "-" & YEAR(B20) -> Q3-2025 | E20: 45874 | F20: =IF(E20<B20,"Invalid RequiredDate","Valid") -> Valid | G20: =MEDIAN($E$2:$E$633-$B$2:$B$633) -> 16 | H20: =IF(E20<B20,B20+$G$2,E20) -> 45874 | I20: Americas | J20: =I20 & " → " & L20 & " → " & M20 -> Americas → Brazil → Brasília | K20: =L20 & "-" & TEXT(C20,"YYYY-MM") -> Brazil-2025-07 | L20: Brazil | M20: Brasília | N20: Enterprise | O20: Marketplace | P20: G. Dubois | Q20: Accessories | R20: ACC-8098 | S20: 1068.17 | T20: 2375.37 | U20: =IF(T20<0,"Invalid Price","Valid") -> Valid | V20: =IF(T20<0,AVERAGEIF($Q$2:$Q$633,Q20,$T$2:$T$633),T20) -> 2375.37 | W20: =IF(V20<=616.86,"Low",IF(V20<1912.05,"Medium","High")) -> High | X20: 0.109 | Y20: =IF(X20>30%,"High Discount","Valid") -> Valid | Z20: =IF(X20>30%,30%,X20) -> 0.109 | AA20: 18 | AB20: =V20 * AA20 * (1 - Z20) -> 38096.184 | AC20: =S20*AA20 -> 19227.06 | AD20: =AB20-AC20 -> 18869.124 | AE20: =IF(AB20=0, 0, AD20 / AB20) -> 0.49530221 | AF20: =IF(G20<=7,1,0) -> 0 | AG20: =IF(Z20>20%,1,0) -> 0 | AJ20: =MIN(IF($L$2:$L$633=L2,$B$2:$B$633)) -> 0 | AK20: =AA20*(1+What_if_Analysis!$B$4) -> 21.6 | AL20: =MIN(Z20,What_if_Analysis!$B$2) -> 0.05 | AM20: =AK20*V20*(1-AL20) -> 48742.592 | AN20: =AM20-(AK20*(T20*(1+What_if_Analysis!$B$3))) -> -7696.1988
A21: ORD-2025-745263 | B21: 45798 | C21: =TEXT(B21,"mmm-yyyy") -> May-2025 | D21: ="Q" & ROUNDUP(MONTH(B21)/3,0) & "-" & YEAR(B21) -> Q2-2025 | E21: 45796 | F21: =IF(E21<B21,"Invalid RequiredDate","Valid") -> Invalid RequiredDate | G21: =MEDIAN($E$2:$E$633-$B$2:$B$633) -> -2 | H21: =IF(E21<B21,B21+$G$2,E21) -> 45824 | I21: Europe | J21: =I21 & " → " & L21 & " → " & M21 -> Europe → United Kingdom → Birmingham | K21: =L21 & "-" & TEXT(C21,"YYYY-MM") -> United Kingdom-2025-05 | L21: United Kingdom | M21: Birmingham | N21: Enterprise | O21: Online | P21: M. Rossi | Q21: Laptops | R21: LAP-3385 | S21: 1015.16 | T21: 2148.14 | U21: =IF(T21<0,"Invalid Price","Valid") -> Valid | V21: =IF(T21<0,AVERAGEIF($Q$2:$Q$633,Q21,$T$2:$T$633),T21) -> 2148.14 | W21: =IF(V21<=616.86,"Low",IF(V21<1912.05,"Medium","High")) -> High | X21: 0.038 | Y21: =IF(X21>30%,"High Discount","Valid") -> Valid | Z21: =IF(X21>30%,30%,X21) -> 0.038 | AA21: 19 | AB21: =V21 * AA21 * (1 - Z21) -> 39263.703 | AC21: =S21*AA21 -> 19288.04 | AD21: =AB21-AC21 -> 19975.663 | AE21: =IF(AB21=0, 0, AD21 / AB21) -> 0.50875647 | AF21: =IF(G21<=7,1,0) -> 1 | AG21: =IF(Z21>20%,1,0) -> 0 | AK21: =AA21*(1+What_if_Analysis!$B$4) -> 22.8 | AL21: =MIN(Z21,What_if_Analysis!$B$2) -> 0.038 | AM21: =AK21*V21*(1-AL21) -> 47116.444 | AN21: =AM21-(AK21*(T21*(1+What_if_Analysis!$B$3))) -> -6758.9077
A22: ORD-2024-798002 | B22: 45498 | C22: =TEXT(B22,"mmm-yyyy") -> Jul-2024 | D22: ="Q" & ROUNDUP(MONTH(B22)/3,0) & "-" & YEAR(B22) -> Q3-2024 | E22: 45497 | F22: =IF(E22<B22,"Invalid RequiredDate","Valid") -> Invalid RequiredDate | G22: =MEDIAN($E$2:$E$633-$B$2:$B$633) -> -1 | H22: =IF(E22<B22,B22+$G$2,E22) -> 45524 | I22: Africa | J22: =I22 & " → " & L22 & " → " & M22 -> Africa → Kenya → Mombasa | K22: =L22 & "-" & TEXT(C22,"YYYY-MM") -> Kenya-2024-07 | L22: Kenya | M22: Mombasa | N22: Non-Profit | O22: Direct | P22: J. Njeri | Q22: Laptops | R22: LAP-9815 | S22: 1494.4 | T22: 3661.07 | U22: =IF(T22<0,"Invalid Price","Valid") -> Valid | V22: =IF(T22<0,AVERAGEIF($Q$2:$Q$633,Q22,$T$2:$T$633),T22) -> 3661.07 | W22: =IF(V22<=616.86,"Low",IF(V22<1912.05,"Medium","High")) -> High | X22: 0.072 | Y22: =IF(X22>30%,"High Discount","Valid") -> Valid | Z22: =IF(X22>30%,30%,X22) -> 0.072 | AA22: 7 | AB22: =V22 * AA22 * (1 - Z22) -> 23782.311 | AC22: =S22*AA22 -> 10460.8 | AD22: =AB22-AC22 -> 13321.511 | AE22: =IF(AB22=0, 0, AD22 / AB22) -> 0.56014367 | AF22: =IF(G22<=7,1,0) -> 1 | AG22: =IF(Z22>20%,1,0) -> 0 | AK22: =AA22*(1+What_if_Analysis!$B$4) -> 8.4 | AL22: =MIN(Z22,What_if_Analysis!$B$2) -> 0.05 | AM22: =AK22*V22*(1-AL22) -> 29215.339 | AN22: =AM22-(AK22*(T22*(1+What_if_Analysis!$B$3))) -> -4612.9482
A23: ORD-2023-867836 | B23: 45057 | C23: =TEXT(B23,"mmm-yyyy") -> May-2023 | D23: ="Q" & ROUNDUP(MONTH(B23)/3,0) & "-" & YEAR(B23) -> Q2-2023 | E23: 45074 | F23: =IF(E23<B23,"Invalid RequiredDate","Valid") -> Valid | G23: =MEDIAN($E$2:$E$633-$B$2:$B$633) -> 17 | H23: =IF(E23<B23,B23+$G$2,E23) -> 45074 | I23: Asia | J23: =I23 & " → " & L23 & " → " & M23 -> Asia → China → Shenzhen | K23: =L23 & "-" & TEXT(C23,"YYYY-MM") -> China-2023-05 | L23: China | M23: Shenzhen | N23: Enterprise | O23: Marketplace | P23: E. Garcia | Q23: Networking | R23: NET-3255 | S23: 1331.19 | T23: 2903.09 | U23: =IF(T23<0,"Invalid Price","Valid") -> Valid | V23: =IF(T23<0,AVERAGEIF($Q$2:$Q$633,Q23,$T$2:$T$633),T23) -> 2903.09 | W23: =IF(V23<=616.86,"Low",IF(V23<1912.05,"Medium","High")) -> High | X23: 0.143 | Y23: =IF(X23>30%,"High Discount","Valid") -> Valid | Z23: =IF(X23>30%,30%,X23) -> 0.143 | AA23: 8 | AB23: =V23 * AA23 * (1 - Z23) -> 19903.585 | AC23: =S23*AA23 -> 10649.52 | AD23: =AB23-AC23 -> 9254.065 | AE23: =IF(AB23=0, 0, AD23 / AB23) -> 0.46494463 | AF23: =IF(G23<=7,1,0) -> 0 | AG23: =IF(Z23>20%,1,0) -> 0 | AK23: =AA23*(1+What_if_Analysis!$B$4) -> 9.6 | AL23: =MIN(Z23,What_if_Analysis!$B$2) -> 0.05 | AM23: =AK23*V23*(1-AL23) -> 26476.181 | AN23: =AM23-(AK23*(T23*(1+What_if_Analysis!$B$3))) -> -4180.4496
A24: ORD-2025-580047 | B24: 45822 | C24: =TEXT(B24,"mmm-yyyy") -> Jun-2025 | D24: ="Q" & ROUNDUP(MONTH(B24)/3,0) & "-" & YEAR(B24) -> Q2-2025 | E24: 45837 | F24: =IF(E24<B24,"Invalid RequiredDate","Valid") -> Valid | G24: =MEDIAN($E$2:$E$633-$B$2:$B$633) -> 15 | H24: =IF(E24<B24,B24+$G$2,E24) -> 45837 | I24: Africa | J24: =I24 & " → " & L24 & " → " & M24 -> Africa → Nigeria → Port Harcourt | K24: =L24 & "-" & TEXT(C24,"YYYY-MM") -> Nigeria-2025-06 | L24: Nigeria | M24: Port Harcourt | N24: Consumer | O24: Marketplace | P24: M. Rossi | Q24: Accessories | R24: ACC-3961 | S24: 730.99 | T24: 1242.84 | U24: =IF(T24<0,"Invalid Price","Valid") -> Valid | V24: =IF(T24<0,AVERAGEIF($Q$2:$Q$633,Q24,$T$2:$T$633),T24) -> 1242.84 | W24: =IF(V24<=616.86,"Low",IF(V24<1912.05,"Medium","High")) -> Medium | X24: 0.12 | Y24: =IF(X24>30%,"High Discount","Valid") -> Valid | Z24: =IF(X24>30%,30%,X24) -> 0.12 | AA24: 10 | AB24: =V24 * AA24 * (1 - Z24) -> 10936.992 | AC24: =S24*AA24 -> 7309.9 | AD24: =AB24-AC24 -> 3627.092 | AE24: =IF(AB24=0, 0, AD24 / AB24) -> 0.33163524 | AF24: =IF(G24<=7,1,0) -> 0 | AG24: =IF(Z24>20%,1,0) -> 0 | AK24: =AA24*(1+What_if_Analysis!$B$4) -> 12 | AL24: =MIN(Z24,What_if_Analysis!$B$2) -> 0.05 | AM24: =AK24*V24*(1-AL24) -> 14168.376 | AN24: =AM24-(AK24*(T24*(1+What_if_Analysis!$B$3))) -> -2237.112
A25: ORD-2024-500109 | B25: 45430 | C25: =TEXT(B25,"mmm-yyyy") -> May-2024 | D25: ="Q" & ROUNDUP(MONTH(B25)/3,0) & "-" & YEAR(B25) -> Q2-2024 | E25: 45435 | F25: =IF(E25<B25,"Invalid RequiredDate","Valid") -> Valid | G25: =MEDIAN($E$2:$E$633-$B$2:$B$633) -> 5 | H25: =IF(E25<B25,B25+$G$2,E25) -> 45435 | I25: Americas | J25: =I25 & " → " & L25 & " → " & M25 -> Americas → USA → Chicago | K25: =L25 & "-" & TEXT(C25,"YYYY-MM") -> USA-2024-05 | L25: USA | M25: Chicago | N25: Enterprise | O25: Retail | P25: H. Kim | Q25: Laptops | R25: LAP-4987 | S25: 1274.59 | T25: 2553.69 | U25: =IF(T25<0,"Invalid Price","Valid") -> Valid | V25: =IF(T25<0,AVERAGEIF($Q$2:$Q$633,Q25,$T$2:$T$633),T25) -> 2553.69 | W25: =IF(V25<=616.86,"Low",IF(V25<1912.05,"Medium","High")) -> High | X25: 0.01 | Y25: =IF(X25>30%,"High Discount","Valid") -> Valid | Z25: =IF(X25>30%,30%,X25) -> 0.01 | AA25: 8 | AB25: =V25 * AA25 * (1 - Z25) -> 20225.225 | AC25: =S25*AA25 -> 10196.72 | AD25: =AB25-AC25 -> 10028.505 | AE25: =IF(AB25=0, 0, AD25 / AB25) -> 0.49584145 | AF25: =IF(G25<=7,1,0) -> 1 | AG25: =IF(Z25>20%,1,0) -> 0 | AK25: =AA25*(1+What_if_Analysis!$B$4) -> 9.6 | AL25: =MIN(Z25,What_if_Analysis!$B$2) -> 0.01 | AM25: =AK25*V25*(1-AL25) -> 24270.27 | AN25: =AM25-(AK25*(T25*(1+What_if_Analysis!$B$3))) -> -2696.6966
A26: ORD-2023-271836 | B26: 44964 | C26: =TEXT(B26,"mmm-yyyy") -> Feb-2023 | D26: ="Q" & ROUNDUP(MONTH(B26)/3,0) & "-" & YEAR(B26) -> Q1-2023 | E26: 44969 | F26: =IF(E26<B26,"Invalid RequiredDate","Valid") -> Valid | G26: =MEDIAN($E$2:$E$633-$B$2:$B$633) -> 5 | H26: =IF(E26<B26,B26+$G$2,E26) -> 44969 | I26: Americas | J26: =I26 & " → " & L26 & " → " & M26 -> Americas → Brazil → São Paulo | K26: =L26 & "-" & TEXT(C26,"YYYY-MM") -> Brazil-2023-02 | L26: Brazil | M26: São Paulo | N26: Education | O26: Online | P26: N. Brown | Q26: Components | R26: CMP-2693 | S26: 948.55 | T26: 2089.16 | U26: =IF(T26<0,"Invalid Price","Valid") -> Valid | V26: =IF(T26<0,AVERAGEIF($Q$2:$Q$633,Q26,$T$2:$T$633),T26) -> 2089.16 | W26: =IF(V26<=616.86,"Low",IF(V26<1912.05,"Medium","High")) -> High | X26: 0.007 | Y26: =IF(X26>30%,"High Discount","Valid") -> Valid | Z26: =IF(X26>30%,30%,X26) -> 0.007 | AA26: 12 | AB26: =V26 * AA26 * (1 - Z26) -> 24894.431 | AC26: =S26*AA26 -> 11382.6 | AD26: =AB26-AC26 -> 13511.831 | AE26: =IF(AB26=0, 0, AD26 / AB26) -> 0.5427652 | AF26: =IF(G26<=7,1,0) -> 1 | AG26: =IF(Z26>20%,1,0) -> 0 | AK26: =AA26*(1+What_if_Analysis!$B$4) -> 14.4 | AL26: =MIN(Z26,What_if_Analysis!$B$2) -> 0.007 | AM26: =AK26*V26*(1-AL26) -> 29873.317 | AN26: =AM26-(AK26*(T26*(1+What_if_Analysis!$B$3))) -> -3218.9777
A27: ORD-2024-215294 | B27: 45473 | C27: =TEXT(B27,"mmm-yyyy") -> Jun-2024 | D27: ="Q" & ROUNDUP(MONTH(B27)/3,0) & "-" & YEAR(B27) -> Q2-2024 | E27: 45487 | F27: =IF(E27<B27,"Invalid RequiredDate","Valid") -> Valid | G27: =MEDIAN($E$2:$E$633-$B$2:$B$633) -> 14 | H27: =IF(E27<B27,B27+$G$2,E27) -> 45487 | I27: Americas | J27: =I27 & " → " & L27 & " → " & M27 -> Americas → Brazil → Brasília | K27: =L27 & "-" & TEXT(C27,"YYYY-MM") -> Brazil-2024-06 | L27: Brazil | M27: Brasília | N27: Education | O27: Retail | P27: C. Otieno | Q27: Accessories | R27: ACC-8683 | S27: 1491.85 | T27: 2583.02 | U27: =IF(T27<0,"Invalid Price","Valid") -> Valid | V27: =IF(T27<0,AVERAGEIF($Q$2:$Q$633,Q27,$T$2:$T$633),T27) -> 2583.02 | W27: =IF(V27<=616.86,"Low",IF(V27<1912.05,"Medium","High")) -> High | X27: 0.168 | Y27: =IF(X27>30%,"High Discount","Valid") -> Valid | Z27: =IF(X27>30%,30%,X27) -> 0.168 | AA27: 4 | AB27: =V27 * AA27 * (1 - Z27) -> 8596.2906 | AC27: =S27*AA27 -> 5967.4 | AD27: =AB27-AC27 -> 2628.8906 | AE27: =IF(AB27=0, 0, AD27 / AB27) -> 0.30581686 | AF27: =IF(G27<=7,1,0) -> 0 | AG27: =IF(Z27>20%,1,0) -> 0 | AK27: =AA27*(1+What_if_Analysis!$B$4) -> 4.8 | AL27: =MIN(Z27,What_if_Analysis!$B$2) -> 0.05 | AM27: =AK27*V27*(1-AL27) -> 11778.571 | AN27: =AM27-(AK27*(T27*(1+What_if_Analysis!$B$3))) -> -1859.7744
A28: ORD-2024-788105 | B28: 45626 | C28: =TEXT(B28,"mmm-yyyy") -> Nov-2024 | D28: ="Q" & ROUNDUP(MONTH(B28)/3,0) & "-" & YEAR(B28) -> Q4-2024 | E28: 45656 | F28: =IF(E28<B28,"Invalid RequiredDate","Valid") -> Valid | G28: =MEDIAN($E$2:$E$633-$B$2:$B$633) -> 30 | H28: =IF(E28<B28,B28+$G$2,E28) -> 45656 | I28: Europe | J28: =I28 & " → " & L28 & " → " & M28 -> Europe → France → Marseille | K28: =L28 & "-" & TEXT(C28,"YYYY-MM") -> France-2024-11 | L28: France | M28: Marseille | N28: Consumer | O28: Marketplace | P28: F. Müller | Q28: Printers | R28: PRN-4170 | S28: 117.64 | T28: 175.67 | U28: =IF(T28<0,"Invalid Price","Valid") -> Valid | V28: =IF(T28<0,AVERAGEIF($Q$2:$Q$633,Q28,$T$2:$T$633),T28) -> 175.67 | W28: =IF(V28<=616.86,"Low",IF(V28<1912.05,"Medium","High")) -> Low | X28: 0 | Y28: =IF(X28>30%,"High Discount","Valid") -> Valid | Z28: =IF(X28>30%,30%,X28) -> 0 | AA28: 10 | AB28: =V28 * AA28 * (1 - Z28) -> 1756.7 | AC28: =S28*AA28 -> 1176.4 | AD28: =AB28-AC28 -> 580.3 | AE28: =IF(AB28=0, 0, AD28 / AB28) -> 0.33033529 | AF28: =IF(G28<=7,1,0) -> 0 | AG28: =IF(Z28>20%,1,0) -> 0 | AK28: =AA28*(1+What_if_Analysis!$B$4) -> 12 | AL28: =MIN(Z28,What_if_Analysis!$B$2) -> 0 | AM28: =AK28*V28*(1-AL28) -> 2108.04 | AN28: =AM28-(AK28*(T28*(1+What_if_Analysis!$B$3))) -> -210.804
A29: ORD-2024-855073 | B29: 45492 | C29: =TEXT(B29,"mmm-yyyy") -> Jul-2024 | D29: ="Q" & ROUNDUP(MONTH(B29)/3,0) & "-" & YEAR(B29) -> Q3-2024 | E29: 45492 | F29: =IF(E29<B29,"Invalid RequiredDate","Valid") -> Valid | G29: =MEDIAN($E$2:$E$633-$B$2:$B$633) -> 0 | H29: =IF(E29<B29,B29+$G$2,E29) -> 45492 | I29: Africa | J29: =I29 & " → " & L29 & " → " & M29 -> Africa → Kenya → Kisumu | K29: =L29 & "-" & TEXT(C29,"YYYY-MM") -> Kenya-2024-07 | L29: Kenya | M29: Kisumu | N29: Small Business | O29: Retail | P29: A. Patel | Q29: Phones | R29: PHN-6854 | S29: 857.24 | T29: 758.23 | U29: =IF(T29<0,"Invalid Price","Valid") -> Valid | V29: =IF(T29<0,AVERAGEIF($Q$2:$Q$633,Q29,$T$2:$T$633),T29) -> 758.23 | W29: =IF(V29<=616.86,"Low",IF(V29<1912.05,"Medium","High")) -> Medium | X29: 0.125 | Y29: =IF(X29>30%,"High Discount","Valid") -> Valid | Z29: =IF(X29>30%,30%,X29) -> 0.125 | AA29: 6 | AB29: =V29 * AA29 * (1 - Z29) -> 3980.7075 | AC29: =S29*AA29 -> 5143.44 | AD29: =AB29-AC29 -> -1162.7325 | AE29: =IF(AB29=0, 0, AD29 / AB29) -> -0.29209192 | AF29: =IF(G29<=7,1,0) -> 1 | AG29: =IF(Z29>20%,1,0) -> 0 | AK29: =AA29*(1+What_if_Analysis!$B$4) -> 7.2 | AL29: =MIN(Z29,What_if_Analysis!$B$2) -> 0.05 | AM29: =AK29*V29*(1-AL29) -> 5186.2932 | AN29: =AM29-(AK29*(T29*(1+What_if_Analysis!$B$3))) -> -818.8884
A30: ORD-2023-897079 | B30: 45030 | C30: =TEXT(B30,"mmm-yyyy") -> Apr-2023 | D30: ="Q" & ROUNDUP(MONTH(B30)/3,0) & "-" & YEAR(B30) -> Q2-2023 | E30: 45060 | F30: =IF(E30<B30,"Invalid RequiredDate","Valid") -> Valid | G30: =MEDIAN($E$2:$E$633-$B$2:$B$633) -> 30 | H30: =IF(E30<B30,B30+$G$2,E30) -> 45060 | I30: Africa | J30: =I30 & " → " & L30 & " → " & M30 -> Africa → Kenya → Nakuru | K30: =L30 & "-" & TEXT(C30,"YYYY-MM") -> Kenya-2023-04 | L30: Kenya | M30: Nakuru | N30: Consumer | O30: Marketplace | P30: M. Rossi | Q30: Phones | R30: PHN-1784 | S30: 209.25 | T30: 434.8 | U30: =IF(T30<0,"Invalid Price","Valid") -> Valid | V30: =IF(T30<0,AVERAGEIF($Q$2:$Q$633,Q30,$T$2:$T$633),T30) -> 434.8 | W30: =IF(V30<=616.86,"Low",IF(V30<1912.05,"Medium","High")) -> Low | X30: 0 | Y30: =IF(X30>30%,"High Discount","Valid") -> Valid | Z30: =IF(X30>30%,30%,X30) -> 0 | AA30: 9 | AB30: =V30 * AA30 * (1 - Z30) -> 3913.2 | AC30: =S30*AA30 -> 1883.25 | AD30: =AB30-AC30 -> 2029.95 | AE30: =IF(AB30=0, 0, AD30 / AB30) -> 0.51874425 | AF30: =IF(G30<=7,1,0) -> 0 | AG30: =IF(Z30>20%,1,0) -> 0 | AK30: =AA30*(1+What_if_Analysis!$B$4) -> 10.8 | AL30: =MIN(Z30,What_if_Analysis!$B$2) -> 0 | AM30: =AK30*V30*(1-AL30) -> 4695.84 | AN30: =AM30-(AK30*(T30*(1+What_if_Analysis!$B$3))) -> -469.584
A31: ORD-2025-548982 | B31: 45754 | C31: =TEXT(B31,"mmm-yyyy") -> Apr-2025 | D31: ="Q" & ROUNDUP(MONTH(B31)/3,0) & "-" & YEAR(B31) -> Q2-2025 | E31: 45758 | F31: =IF(E31<B31,"Invalid RequiredDate","Valid") -> Valid | G31: =MEDIAN($E$2:$E$633-$B$2:$B$633) -> 4 | H31: =IF(E31<B31,B31+$G$2,E31) -> 45758 | I31: Europe | J31: =I31 & " → " & L31 & " → " & M31 -> Europe → France → Lyon | K31: =L31 & "-" & TEXT(C31,"YYYY-MM") -> France-2025-04 | L31: France | M31: Lyon | N31: Education | O31: Retail | P31: E. Garcia | Q31: Networking | R31: NET-9716 | S31: 754.77 | T31: 1666.18 | U31: =IF(T31<0,"Invalid Price","Valid") -> Valid | V31: =IF(T31<0,AVERAGEIF($Q$2:$Q$633,Q31,$T$2:$T$633),T31) -> 1666.18 | W31: =IF(V31<=616.86,"Low",IF(V31<1912.05,"Medium","High")) -> Medium | X31: 0.139 | Y31: =IF(X31>30%,"High Discount","Valid") -> Valid | Z31: =IF(X31>30%,30%,X31) -> 0.139 | AA31: 14 | AB31: =V31 * AA31 * (1 - Z31) -> 20084.134 | AC31: =S31*AA31 -> 10566.78 | AD31: =AB31-AC31 -> 9517.3537 | AE31: =IF(AB31=0, 0, AD31 / AB31) -> 0.47387425 | AF31: =IF(G31<=7,1,0) -> 1 | AG31: =IF(Z31>20%,1,0) -> 0 | AK31: =AA31*(1+What_if_Analysis!$B$4) -> 16.8 | AL31: =MIN(Z31,What_if_Analysis!$B$2) -> 0.05 | AM31: =AK31*V31*(1-AL31) -> 26592.233 | AN31: =AM31-(AK31*(T31*(1+What_if_Analysis!$B$3))) -> -4198.7736
A32: ORD-2024-170313 | B32: 45653 | C32: =TEXT(B32,"mmm-yyyy") -> Dec-2024 | D32: ="Q" & ROUNDUP(MONTH(B32)/3,0) & "-" & YEAR(B32) -> Q4-2024 | E32: 45672 | F32: =IF(E32<B32,"Invalid RequiredDate","Valid") -> Valid | G32: =MEDIAN($E$2:$E$633-$B$2:$B$633) -> 19 | H32: =IF(E32<B32,B32+$G$2,E32) -> 45672 | I32: Asia | J32: =I32 & " → " & L32 & " → " & M32 -> Asia → India → Delhi | K32: =L32 & "-" & TEXT(C32,"YYYY-MM") -> India-2024-12 | L32: India | M32: Delhi | N32: Non-Profit | O32: Distributor | P32: G. Dubois | Q32: Components | R32: CMP-6919 | S32: 495.59 | T32: 631.78 | U32: =IF(T32<0,"Invalid Price","Valid") -> Valid | V32: =IF(T32<0,AVERAGEIF($Q$2:$Q$633,Q32,$T$2:$T$633),T32) -> 631.78 | W32: =IF(V32<=616.86,"Low",IF(V32<1912.05,"Medium","High")) -> Medium | X32: 0.087 | Y32: =IF(X32>30%,"High Discount","Valid") -> Valid | Z32: =IF(X32>30%,30%,X32) -> 0.087 | AA32: 17 | AB32: =V32 * AA32 * (1 - Z32) -> 9805.8574 | AC32: =S32*AA32 -> 8425.03 | AD32: =AB32-AC32 -> 1380.8274 | AE32: =IF(AB32=0, 0, AD32 / AB32) -> 0.14081659 | AF32: =IF(G32<=7,1,0) -> 0 | AG32: =IF(Z32>20%,1,0) -> 0 | AK32: =AA32*(1+What_if_Analysis!$B$4) -> 20.4 | AL32: =MIN(Z32,What_if_Analysis!$B$2) -> 0.05 | AM32: =AK32*V32*(1-AL32) -> 12243.896 | AN32: =AM32-(AK32*(T32*(1+What_if_Analysis!$B$3))) -> -1933.2468
... A633: ORD-2025-728935 | B633: 45716 | C633: =TEXT(B633,"mmm-yyyy") -> Feb-2025 | D633: ="Q" & ROUNDUP(MONTH(B633)/3,0) & "-" & YEAR(B633) -> Q1-2025 | E633: 45726 | F633: =IF(E633<B633,"Invalid RequiredDate","Valid") -> Valid | G633: =MEDIAN($E$2:$E$633-$B$2:$B$633) -> 10 | H633: =IF(E633<B633,B633+$G$2,E633) -> 45726 | I633: Asia | J633: =I633 & " → " & L633 & " → " & M633 -> Asia → Japan → Osaka | K633: =L633 & "-" & TEXT(C633,"YYYY-MM") -> Japan-2025-02 | L633: Japan | M633: Osaka | N633: Education | O633: Distributor | P633: N. Brown | Q633: Laptops | R633: LAP-3017 | S633: 51.86 | T633: 45.98 | U633: =IF(T633<0,"Invalid Price","Valid") -> Valid | V633: =IF(T633<0,AVERAGEIF($Q$2:$Q$633,Q633,$T$2:$T$633),T633) -> 45.98 | W633: =IF(V633<=616.86,"Low",IF(V633<1912.05,"Medium","High")) -> Low | X633: 0.173 | Y633: =IF(X633>30%,"High Discount","Valid") -> Valid | Z633: =IF(X633>30%,30%,X633) -> 0.173 | AA633: 7 | AB633: =V633 * AA633 * (1 - Z633) -> 266.17822 | AC633: =S633*AA633 -> 363.02 | AD633: =AB633-AC633 -> -96.84178 | AE633: =IF(AB633=0, 0, AD633 / AB633) -> -0.36382308 | AF633: =IF(G633<=7,1,0) -> 0 | AG633: =IF(Z633>20%,1,0) -> 0 | AK633: =AA633*(1+What_if_Analysis!$B$4) -> 8.4 | AL633: =MIN(Z633,What_if_Analysis!$B$2) -> 0.05 | AM633: =AK633*V633*(1-AL633) -> 366.9204 | AN633: =AM633-(AK633*(T633*(1+What_if_Analysis!$B$3))) -> -57.9348
A634: =COUNT(A2:A633) -> 0 | AB634: =SUM(AB2:AB633) -> 11053963 | AD634: =SUM(AD2:AD633) -> 3526215.3 | AF634: =AVERAGE(AF2:AF633) -> 0.2721519 | AM634: =SUM(AM2:AM633) -> 14471022 | AN634: =SUM(AN2:AN633) -> -2013483.4

Sheet README
A2: Issue | B2: Missing Value Handling Rules
A3: Missing City | B3: Reviewed using Region and Country information. Records where city could not be confidently determined were labelled "Unknown".
A4: Missing Salesperson | B4: Replaced with "Unassigned" because transactions should remain in analysis without incorrectly assigning ownership.
A5: Missing Channel | B5: Filled using the most common channel for similar Region/ProductCategory combinations. Where unavailable, labelled "Unknown".
A8: Suspicious Price and Discount Handling
A10: UnitPrice:
A11: Negative UnitPrice values were flagged as invalid because selling prices cannot be below zero. Invalid prices were corrected using the median valid UnitPrice within the same ProductCategory to maintain realistic pricing patterns.
A13: DiscountPct:
A14: Discount values above 30% were flagged as suspicious. These values were capped at 30%, based on the assumption that discounts above this level represent data entry errors or exceptional cases requiring correction.
A19: RequiredDate Correction Approach:
A20: The dataset was checked to ensure that RequiredDate was not earlier than OrderDate. Any records where RequiredDate occurred before OrderDate were flagged as invalid because they represented unrealistic delivery timelines.
A22: To correct these records, the normal delivery duration was calculated from valid transactions only by finding the difference between RequiredDate and OrderDate. The median of these valid lead times was calculated to represent the typical delivery period in the dataset.
A24: The calculated median lead time was 26 days. For invalid records, the original RequiredDate was replaced by adding the 26-day median lead time to the OrderDate. Valid RequiredDate values were retained without changes.
A26: Formula logic used:
A28: If RequiredDate < OrderDate → Clean RequiredDate = OrderDate + Median Lead Time
A29: Otherwise → Clean RequiredDate = Original RequiredDate
A31: This approach preserves the overall delivery pattern in the data while correcting unrealistic dates without using arbitrary assumptions.
B33: CHANNEL MIX AND CANNIBALIZATION
A34: Channel mix varies significantly across regions. Africa and Asia remain predominantly offline-driven, with Distributor and Retail channels contributing the majority of revenue. In contrast, Americas shows a strong digital shift, where Online revenue (689K) significantly exceeds Retail (302K), suggesting potential cannibalization of retail by online channels. Europe exhibits a balanced channel distribution, with Direct and Marketplace channels leading, and only mild substitution effects between Online and Retail.
B36: PRICE COMPLIANCE
B37: Price compliance varies significantly across regions and salespeople. Certain salespeople in the Americas and Europe exhibit high proportions of orders with discounts above 20%, exceeding 30% in some cases, indicating potential pricing leakage or aggressive discounting behavior. In contrast, Africa shows relatively lower incidence of high discounts, suggesting stronger pricing discipline. These patterns highlight inconsistency in discount control across the salesforce.
B40: Scenario Modeling Results
B42: The What-If analysis was conducted using the following assumptions:
B44: Global Discount Cap = 5%
B45: Unit Cost Inflation = 10%
B46: Quantity Uplift = 20%
B48: The recalculated Revenue and Profit metrics were compared with the baseline values as shown below:
B50: Metric | C50: Baseline | D50: Scenario | E50: Difference | F50: % Change
B51: Revenue | C51: 7527747.7 | D51: 14471022 | E51: 6943274.8 | F51: 0.9223
B52: Profit | C52: 3526215.3 | D52: -2013483.4 | E52: -5539698.7 | F52: -1.571
B54: Interpretation
B56: Under the scenario assumptions, revenue increased from 7.53 million to 14.47 million, representing a 92.23% increase compared to the baseline. However, profit declined from 3.53 million to a loss of 2.01 million, representing a 157.10% decrease. This indicates that although sales revenue improved significantly under the scenario, the increase in operating costs outweighed the revenue gains, resulting in a substantial reduction in profitability.
B62: Scenario analysis showed that increasing sales volume by 20% while costs rose by 10% generated higher revenue (+92.23%) but reduced profitability, leading to a net loss of KES 2.01 million.
B64: One note: before submitting, I would still verify the ScenarioRevenue formula because a 20% quantity uplift producing a 92% revenue increase is unusual. If your instructor checks the numbers, it is worth confirming that the scenario formulas are behaving as intended.
